{
    "id": "24bed7eed09723f99df68b059732c0c3383f684d30c24189c6bac289ad0f58e9",
    "type": "other",
    "app_id": "com.garmin.garmin",
    "start_epoch_ms": 1622930623000,
    "end_epoch_ms": 1622930722000,
    "last_modified": 1639998254906,
    "active_duration_ms": 99000,
    "session": false,
    "delete_indicator": false,
    "summaries": [],
    "sources": [],
    "tags": {},
    "change_tokens": [
        "ac9d29cf0b69bdef025a77a7e999a7351c82e307fb56f4c51cc4d83d68a9bded:1639998254906"
    ],
    "metric_types": [],
    "moments": []
}