[{"run_id": 1625334253000, "name": "run from gpx", "distance": 5092.509349567399, "moving_time": "1:14:03", "type": "Run", "start_date": "2021-07-03 17:44:13", "start_date_local": "2021-07-04 01:44:13", "location_country": "Commonwealth Station Exit B/C, Commonwealth Avenue, Queenstown, Northwest, 149735, Singapore", "summary_polyline": "_m}FgbpxRhH_ItAuDt@EbKmMw@gAPu@cA{@Fk@dBoC^qBfGiJdBqKu@}Hv@StANWm@ST?}Ae@pAr@OCVLkALjBpFn@zAt@~J|@MtE|@vBMdAmFpFk@Eo@d@eBI}CgDS~KcBLqD|BwFfFoNfQg@@SjAqApBoLlMu@DuFfD}@Ce@d@iBoA[`@kBBeAjBiAOM_@[b@", "average_heartrate": null, "average_speed": 1.1461871144648659, "streak": 1}, {"run_id": 1636302739000, "name": "run from gpx", "distance": 4614.414383382965, "moving_time": "1:05:27", "type": "Run", "start_date": "2021-11-07 16:32:19", "start_date_local": "2021-11-08 00:32:19", "location_country": "The Star Vista, 1, Vista Exchange Green, Rochester Hill, Queenstown, Singapore, Southwest, 138617, Singapore", "summary_polyline": "sc~FienxRwArC{Ak@yDZ[W_NxQeBlD{DhMmB~Lm@@SbB}@`B}EfEkYnd@~AKpXyc@~EcFfAcEtAcKjFkQrMaQ", "average_heartrate": null, "average_speed": 1.175048225969688, "streak": 1}, {"run_id": 1638119009000, "name": "run from gpx", "distance": 5734.201447842652, "moving_time": "1:08:25", "type": "Run", "start_date": "2021-11-28 17:03:29", "start_date_local": "2021-11-29 01:03:29", "location_country": "Ulu Pandan Park Connector, Ghim Moh, Northwest, 270015, Singapore", "summary_polyline": "mu~Fy}mxRa@nAqJjMkFbPoBrLf@f@c@hCsFbG{Wbc@kBh@y@G?~A`@N}@rBuJhKgC`AdADHb@l@o@uCaCs@`A\\AwAn@pA]hH{FjEiFlB[QsBl@?v@{@tNuT`AMpHkLxEyEhAcEpAsKxEkPhNuQ", "average_heartrate": null, "average_speed": 1.3968822041029603, "streak": 1}, {"run_id": 1638273357000, "name": "run from gpx", "distance": 3567.703934797271, "moving_time": "0:49:44", "type": "Run", "start_date": "2021-11-30 11:55:57", "start_date_local": "2021-11-30 19:55:57", "location_country": "6, Holland Close, Queenstown, Singapore, Northwest, 271006, Singapore", "summary_polyline": "qf~FcpoxR_Az@nArA@VUSPhDe@ObBnByDnFAlClImBzCiCpC_A~EDnA_@fA|AlB_Ar@HoA`@bAyFy@xCf@|Bp@P?\\Lw@_AhA{@eAbA_Hd@g@k@YKq@m[pNkEjAFqAcAy@\\[eACl@|@_@g@jEeFWc@^}A{AwCv@_BiDoBBaA", "average_heartrate": null, "average_speed": 1.1956112382028388, "streak": 2}, {"run_id": 1639385462000, "name": "run from gpx", "distance": 2180.4374107280432, "moving_time": "0:22:03", "type": "Run", "start_date": "2021-12-13 08:51:02", "start_date_local": "2021-12-13 16:51:02", "location_country": "Commonwealth Lane, Ghim Moh, Northwest, 149555, Singapore", "summary_polyline": "w_~Fk`pxRZe@u@U{@vAf@JdA}@u@e@{@tAb@LjAy@{@k@w@z@DXf@DfAs@u@k@y@|Ad@DdAs@?Ww@Uw@tAd@HjAq@u@s@}@`AD^b@FfAu@q@o@cAvAh@NhAy@u@k@s@bBd@@fAw@AWy@Us@`AD\\fBs@s@k@_AbADZf@DfA{@y@k@u@~Ad@FdAu@@[s@[aA`Bn@N`A{@?[q@I", "average_heartrate": null, "average_speed": 1.6481008395525647, "streak": 1}, {"run_id": 1641287886000, "name": "run from gpx", "distance": 2502.367625545784, "moving_time": "0:26:32", "type": "Run", "start_date": "2022-01-04 09:18:06", "start_date_local": "2022-01-04 17:18:06", "location_country": "Crescent Green, 111, Commonwealth Crescent, Queenstown, Singapore, Northwest, 140111, Singapore", "summary_polyline": "u`~FmbpxRcAfBh@BfAaAw@_@q@`Bh@C|@aAy@Wk@z@F\\~A_A{@[m@bAH\\~AeA}@[m@`AFX`B}@u@a@q@fAHZdBaAaAa@k@`Bj@?|@aA{@e@i@hBb@?|@_Ay@_@o@vAd@Ff@m@c@g@i@lAf@H`A_AAWu@Oq@bAJ`@dBeAaAWm@bAJZbBiA}@Yq@zA`@Ft@e@Rm@y@Su@rAt@R|@mAgAKu@dAoA^mAtB", "average_heartrate": null, "average_speed": 1.5718389607699648, "streak": 1}, {"run_id": 1641495442000, "name": "run from gpx", "distance": 2569.2536047600347, "moving_time": "0:26:53", "type": "Run", "start_date": "2022-01-06 18:57:22", "start_date_local": "2022-01-07 02:57:22", "location_country": "Crescent Green, 111, Commonwealth Crescent, Queenstown, Singapore, Northwest, 140111, Singapore", "summary_polyline": "w`~FobpxRo@fBd@?`A}@y@e@y@jAFZj@C|@y@{@c@o@`BhB}@GYq@Kq@dAJ`@|AmAw@Wg@bBzAeAM[e@?o@dAFZdBeAw@_@s@`Bn@Ar@kAq@Sw@jAHXfBgA{@]o@bBb@?hAeA}@]u@hAH^d@EZs@_@a@g@z@LZ|AcA_Aa@k@fAJ\\|AcA{@_@m@bB`AMb@u@{@_@o@lALZ~AeA}@g@_@hBvAgAm@_@Hh@PM]I", "average_heartrate": null, "average_speed": 1.5928416644513543, "streak": 1}, {"run_id": 1641756789000, "name": "run from gpx", "distance": 2825.098537571855, "moving_time": "0:26:56", "type": "Run", "start_date": "2022-01-09 19:33:09", "start_date_local": "2022-01-10 03:33:09", "location_country": "8, Commonwealth Lane, Queenstown, Singapore, Northwest, 149555, Singapore", "summary_polyline": "a`~Fg`pxRd@k@aAU{@vAj@NjAcAAUw@O_AvAh@NjA_AC[y@Iu@`AF\\h@@bAaAw@e@{@dAD^b@DdAaAw@a@}@tAj@NhAcAAUw@Kw@|@Hd@`@?dA}@?]s@Sy@dABd@f@B~@cAq@[w@~@Hb@dBmAaA[s@`AH`@p@Ez@}@_Aa@w@jAH\\d@@dAeA_Aa@o@bAH^jBgAaA_@u@fAH^d@@bAcA{@_@w@bAD\\h@CdA_A_Ag@q@dBh@BbA_AAYw@Ow@fBn@?`Au@@[q@VTS]K", "average_heartrate": null, "average_speed": 1.748204540576643, "streak": 1}]