[{"run_id": 1420627144000, "name": "run from gpx", "distance": 3017.8863234284113, "moving_time": "0:15:28", "type": "Run", "start_date": "2015-01-07 10:39:04", "start_date_local": "2015-01-07 18:39:04", "location_country": "\u5929\u5fc3\u5c9b\u5c0f\u5b66, \u6ee8\u6e56\u4e1c\u8def, \u6d77\u6ca7\u533a, \u53a6\u95e8\u5e02, \u6d77\u6ca7\u533a, \u53a6\u95e8\u5e02, \u798f\u5efa\u7701, 361022, \u4e2d\u56fd", "summary_polyline": "m{mtC}gnoU`ASPwAlBaD|Ag@rMvNwK~NmG_@gHj@sEc@qAnBd@hHj@bB]`C?dFz@pUv@|HdAdDx@?lFmBxBAdD|@bA`Ac@~G", "average_heartrate": null, "average_speed": 3.2520326761082017, "streak": 1}, {"run_id": 1420652405000, "name": "run from gpx", "distance": 1883.698492313767, "moving_time": "0:09:29", "type": "Run", "start_date": "2015-01-07 17:40:05", "start_date_local": "2015-01-08 01:40:05", "location_country": "\u6d77\u6ca7\u533a, \u53a6\u95e8\u5e02, \u6d77\u6ca7\u533a, \u53a6\u95e8\u5e02, \u798f\u5efa\u7701, 361026, \u4e2d\u56fd", "summary_polyline": "ogntCkyjoUbAoHuB}CjC{DZyA_BwGwCqw@v@mChJuL", "average_heartrate": null, "average_speed": 3.310542165753545, "streak": 2}, {"run_id": 1420711833000, "name": "run from gpx", "distance": 3250.1799364093786, "moving_time": "0:18:30", "type": "Run", "start_date": "2015-01-08 10:10:33", "start_date_local": "2015-01-08 18:10:33", "location_country": "\u5929\u5fc3\u5c9b\u5c0f\u5b66, \u6ee8\u6e56\u4e1c\u8def, \u6d77\u6ca7\u533a, \u53a6\u95e8\u5e02, \u6d77\u6ca7\u533a, \u53a6\u95e8\u5e02, \u798f\u5efa\u7701, 361022, \u4e2d\u56fd", "summary_polyline": "k{mtC_hnoUbBeD|ByBz@MlMzLjA[t@\\pd@~d@jGrE_GcFgHwIaAu@c@TyQwPmViW", "average_heartrate": null, "average_speed": 2.928090032801242, "streak": 2}, {"run_id": 1420802429000, "name": "run from gpx", "distance": 2951.7839483150656, "moving_time": "0:15:30", "type": "Run", "start_date": "2015-01-09 11:20:29", "start_date_local": "2015-01-09 19:20:29", "location_country": "\u8297\u57ce\u533a, \u4e1c\u94fa\u5934\u8857\u9053, \u8297\u57ce\u533a, \u6f33\u5dde\u5e02, \u798f\u5efa\u7701, 363005, \u4e2d\u56fd", "summary_polyline": "chrtCmi_mUnETt@{@Ai@o@a@_EUc@RQ|@x@~@bE@j@m@Ak@o@e@wDQ_An@Ap@f@p@tE@d@mAw@_AaEDi@dAFj@b@LbENz@kAk@aAkEMq@z@^jAvEFl@kAw@_AgED[lA^r@~DBp@}@Sy@oE[s@hA~@rA|DGZe@CeAaDc@uALWnAl@n@pDJv@{@", "average_heartrate": null, "average_speed": 3.1739612347473822, "streak": 3}, {"run_id": 1420888359000, "name": "run from gpx", "distance": 3012.650905062954, "moving_time": "0:15:53", "type": "Run", "start_date": "2015-01-10 11:12:39", "start_date_local": "2015-01-10 19:12:39", "location_country": "\u8297\u57ce\u533a, \u4e1c\u94fa\u5934\u8857\u9053, \u8297\u57ce\u533a, \u6f33\u5dde\u5e02, \u798f\u5efa\u7701, 363005, \u4e2d\u56fd", "summary_polyline": "cirtC{i_mUbF^bA]QwAqEm@}@p@DbA^\\pENj@k@e@oA}D]aAl@Cl@j@n@zDL`Aq@I}@_@UkEQc@RKfA`Ax@tDDl@sAa@q@mEYs@bAb@hApENl@k@i@yAkE[q@|@p@rApENb@cAi@kAwDUaAn@b@~ArERj@s@UsAmEWeAdAPdAlEVv@[", "average_heartrate": null, "average_speed": 3.1612286516925012, "streak": 4}, {"run_id": 1421070137000, "name": "run from gpx", "distance": 3941.444649803473, "moving_time": "0:21:18", "type": "Run", "start_date": "2015-01-12 13:42:17", "start_date_local": "2015-01-12 21:42:17", "location_country": "\u5929\u5fc3\u5c9b\u5c0f\u5b66, \u6ee8\u6e56\u4e1c\u8def, \u6d77\u6ca7\u533a, \u53a6\u95e8\u5e02, \u6d77\u6ca7\u533a, \u53a6\u95e8\u5e02, \u798f\u5efa\u7701, 361022, \u4e2d\u56fd", "summary_polyline": "u{mtCwenoUrF_J|APfNjNFbClBh@zCbCn@lAvEhCfWhWbIzFdJzCwTqPiEwGuCuC_ANoGoFwQyQw@}A}EaD_FkG", "average_heartrate": null, "average_speed": 3.08407249593386, "streak": 1}, {"run_id": 1421322976000, "name": "run from gpx", "distance": 4006.3904766257656, "moving_time": "0:20:21", "type": "Run", "start_date": "2015-01-15 11:56:16", "start_date_local": "2015-01-15 19:56:16", "location_country": "\u6ca7\u6797\u4e1c\u4e09\u8def, \u6d77\u6ca7\u533a, \u53a6\u95e8\u5e02, \u6d77\u6ca7\u533a, \u53a6\u95e8\u5e02, \u798f\u5efa\u7701, 361022, \u4e2d\u56fd", "summary_polyline": "yxmtCebnoU}ByD|JoK`x@hx@bIrFhFbCPM_JaFqAMsOcQc@[o@R{b@mc@mFuDoA~A", "average_heartrate": null, "average_speed": 3.2812370815935834, "streak": 1}, {"run_id": 1421492207000, "name": "run from gpx", "distance": 3952.744187973646, "moving_time": "0:20:35", "type": "Run", "start_date": "2015-01-17 10:56:47", "start_date_local": "2015-01-17 18:56:47", "location_country": "\u8297\u57ce\u533a, \u4e1c\u94fa\u5934\u8857\u9053, \u8297\u57ce\u533a, \u6f33\u5dde\u5e02, \u798f\u5efa\u7701, 363005, \u4e2d\u56fd", "summary_polyline": "sdrtCsh_mUzBMPcBs@_@qE?a@r@X`AlEXt@a@IaBiD[cBd@`@~AdE\\v@aAYgAkEQy@f@Aj@x@x@zDDr@}@_@iAkDSmA`@JhBzDRv@SRk@O}@a@ScEKg@r@H~@`@ZfDJdAm@AcA_@]oEIm@bAr@rA~D?l@}@]eAqEYs@z@n@zAhEHj@mAq@}@gEYa@TKfAn@bAlEAj@kAs@y@aEQc@TObAr@v@dEDj@gAk@cAkEOi@jA", "average_heartrate": null, "average_speed": 3.200602581355179, "streak": 1}, {"run_id": 1421668878000, "name": "run from gpx", "distance": 3991.0259696804096, "moving_time": "0:21:24", "type": "Run", "start_date": "2015-01-19 12:01:18", "start_date_local": "2015-01-19 20:01:18", "location_country": "\u6d77\u6ca7\u533a, \u53a6\u95e8\u5e02, \u6d77\u6ca7\u533a, \u53a6\u95e8\u5e02, \u798f\u5efa\u7701, 361022, \u4e2d\u56fd", "summary_polyline": "gomtCirnoUdt@ft@rKzHlKpExItB\\SiMmDqN}GsPmQiADid@ge@", "average_heartrate": null, "average_speed": 3.1082756773211915, "streak": 1}, {"run_id": 1421836489000, "name": "run from gpx", "distance": 3974.8330161410754, "moving_time": "0:22:03", "type": "Run", "start_date": "2015-01-21 10:34:49", "start_date_local": "2015-01-21 18:34:49", "location_country": "\u6d77\u6ca7\u533a, \u53a6\u95e8\u5e02, \u6d77\u6ca7\u533a, \u53a6\u95e8\u5e02, \u798f\u5efa\u7701, 361022, \u4e2d\u56fd", "summary_polyline": "eomtCgrnoUnBfCeCwB|IfIhAdB}KpOuBrBcDWgHp@mHo@a@x@fAfJHdRjAtSdAnHr@^zCwAxD_@fDd@~BdBlBtDdArFDrB{Ap@^rADjEsBd@B|FSHuMb@iD}Ci@iA", "average_heartrate": null, "average_speed": 3.0044089313235642, "streak": 1}, {"run_id": 1427628183000, "name": "run from gpx", "distance": 4995.549090806245, "moving_time": "0:30:57", "type": "Run", "start_date": "2015-03-29 11:23:03", "start_date_local": "2015-03-29 19:23:03", "location_country": "\u5929\u5fc3\u5c9b\u5c0f\u5b66, \u6ee8\u6e56\u4e1c\u8def, \u6d77\u6ca7\u533a, \u53a6\u95e8\u5e02, \u6d77\u6ca7\u533a, \u53a6\u95e8\u5e02, \u798f\u5efa\u7701, 361022, \u4e2d\u56fd", "summary_polyline": "m{mtC{enoUtA_E~BwCv@O`LlJvDvEdCfBdC|DlDbChTtTvKxIfQvGpHtApPjAtCMCgBoFJeOiAmLwCcLsFaKgIkb@gb@cA`@iBiB", "average_heartrate": null, "average_speed": 2.6901179810480587, "streak": 1}, {"run_id": 1429010130000, "name": "run from gpx", "distance": 3995.0450480574023, "moving_time": "0:22:38", "type": "Run", "start_date": "2015-04-14 11:15:30", "start_date_local": "2015-04-14 19:15:30", "location_country": "\u6ca7\u6797\u4e1c\u4e09\u8def, \u6d77\u6ca7\u533a, \u53a6\u95e8\u5e02, \u6d77\u6ca7\u533a, \u53a6\u95e8\u5e02, \u798f\u5efa\u7701, 361022, \u4e2d\u56fd", "summary_polyline": "o{mtC{`noUSt@lB`BjG_GdBiD`Ai@`HdHnAvBjEjCt@tAlUhT|BvCxDhDzIpF|NtF~F~@xPtAdDEKgA_R_AmPaDgKqEiJoH", "average_heartrate": null, "average_speed": 2.941859387376585, "streak": 1}, {"run_id": 1430132446000, "name": "run from gpx", "distance": 4277.505319670297, "moving_time": "0:23:39", "type": "Run", "start_date": "2015-04-27 11:00:46", "start_date_local": "2015-04-27 19:00:46", "location_country": "\u5929\u5fc3\u5c9b\u5c0f\u5b66, \u6ee8\u6e56\u4e1c\u8def, \u6d77\u6ca7\u533a, \u53a6\u95e8\u5e02, \u6d77\u6ca7\u533a, \u53a6\u95e8\u5e02, \u798f\u5efa\u7701, 361022, \u4e2d\u56fd", "summary_polyline": "s|mtCocnoULhCpBbBzKsM`HhGnBpCbDvBdJ~IfVtV`GbE|JpE|KlClUbBbBQOaAgKQgGo@gHmAeHyBiHeD}FaEwLqL", "average_heartrate": null, "average_speed": 3.01445054240331, "streak": 1}, {"run_id": 1431342323000, "name": "run from gpx", "distance": 5004.7274932540995, "moving_time": "0:26:59", "type": "Run", "start_date": "2015-05-11 11:05:23", "start_date_local": "2015-05-11 19:05:23", "location_country": "\u6ca7\u6797\u4e1c\u4e09\u8def, \u6d77\u6ca7\u533a, \u53a6\u95e8\u5e02, \u6d77\u6ca7\u533a, \u53a6\u95e8\u5e02, \u798f\u5efa\u7701, 361022, \u4e2d\u56fd", "summary_polyline": "o{mtCe`noUKf@tAv@jAStJcLxJvKzDpCh_@t_@nGpEtHzDvMpDbS|AdGEfNcB`B_@C_AaMtAqK\\oMq@_IuAoRuHmFeEqN{N", "average_heartrate": null, "average_speed": 3.091246135425633, "streak": 1}, {"run_id": 1431432971000, "name": "run from gpx", "distance": 2823.5373983367454, "moving_time": "0:18:46", "type": "Run", "start_date": "2015-05-12 12:16:11", "start_date_local": "2015-05-12 20:16:11", "location_country": "\u6ca7\u6797\u4e1c\u4e09\u8def, \u6d77\u6ca7\u533a, \u53a6\u95e8\u5e02, \u6d77\u6ca7\u533a, \u53a6\u95e8\u5e02, \u798f\u5efa\u7701, 361022, \u4e2d\u56fd", "summary_polyline": "a|mtC{_noU`BnBTGzBkBtHoJlJtK`f@|e@|GnElNdGhLvBzBHrAs@v@~@tGv@nCe@?y@}@I", "average_heartrate": null, "average_speed": 2.5075820589136284, "streak": 2}, {"run_id": 1431516263000, "name": "run from gpx", "distance": 2500.790400666392, "moving_time": "0:16:17", "type": "Run", "start_date": "2015-05-13 11:24:23", "start_date_local": "2015-05-13 19:24:23", "location_country": "\u6ca7\u6797\u4e1c\u4e09\u8def, \u6d77\u6ca7\u533a, \u53a6\u95e8\u5e02, \u6d77\u6ca7\u533a, \u53a6\u95e8\u5e02, \u798f\u5efa\u7701, 361022, \u4e2d\u56fd", "summary_polyline": "uzmtCi~moUy@?\\R`BX|F{F~A}ClA[xFtFtBbDhC~AdChDvBnAdT~TbJzHnFvClKpDhPpC", "average_heartrate": null, "average_speed": 2.5596626414190298, "streak": 3}, {"run_id": 1431606301000, "name": "run from gpx", "distance": 4029.9827853564343, "moving_time": "0:22:58", "type": "Run", "start_date": "2015-05-14 12:25:01", "start_date_local": "2015-05-14 20:25:01", "location_country": "\u6ca7\u6797\u4e1c\u4e09\u8def, \u6d77\u6ca7\u533a, \u53a6\u95e8\u5e02, \u6d77\u6ca7\u533a, \u53a6\u95e8\u5e02, \u798f\u5efa\u7701, 361022, \u4e2d\u56fd", "summary_polyline": "wzmtCcanoUa@r@dBdBbG}F|A_D~@s@vFjFtAa@xf@~f@rK~HhEpBhMjDrJpAdLLaEBoOqAsMeDuKgFsF}DyEqF", "average_heartrate": null, "average_speed": 2.924515809402347, "streak": 4}, {"run_id": 1431779846000, "name": "run from gpx", "distance": 4988.912400654372, "moving_time": "0:29:26", "type": "Run", "start_date": "2015-05-16 12:37:26", "start_date_local": "2015-05-16 20:37:26", "location_country": "\u6ca7\u6797\u4e1c\u4e09\u8def, \u6d77\u6ca7\u533a, \u53a6\u95e8\u5e02, \u6d77\u6ca7\u533a, \u53a6\u95e8\u5e02, \u798f\u5efa\u7701, 361022, \u4e2d\u56fd", "summary_polyline": "{xmtCeanoUmAhAbBdA`GaG`CiExFhFlBE~g@rg@dI~FvFtCdIhChLfB~NXk@PuCFmUsCsQ_HyKqIod@wd@aAs@_Ad@sAeA", "average_heartrate": null, "average_speed": 2.8249787093173113, "streak": 1}, {"run_id": 1431865612000, "name": "run from gpx", "distance": 5009.353823985151, "moving_time": "0:29:11", "type": "Run", "start_date": "2015-05-17 12:26:52", "start_date_local": "2015-05-17 20:26:52", "location_country": "\u6ca7\u6797\u4e1c\u4e09\u8def, \u6d77\u6ca7\u533a, \u53a6\u95e8\u5e02, \u6d77\u6ca7\u533a, \u53a6\u95e8\u5e02, \u798f\u5efa\u7701, 361022, \u4e2d\u56fd", "summary_polyline": "s{mtCa`noURt@rAj@rCqBtFiIb@@rF~EvAQjf@vf@`MhIzJ~DpG|AdI`ApM\\oHNcAc@wPiBqSmHqh@{f@gM{N", "average_heartrate": null, "average_speed": 2.8608531262051122, "streak": 2}, {"run_id": 1431953466000, "name": "run from gpx", "distance": 5024.193136780285, "moving_time": "0:28:38", "type": "Run", "start_date": "2015-05-18 12:51:06", "start_date_local": "2015-05-18 20:51:06", "location_country": "\u6ca7\u6797\u4e1c\u4e09\u8def, \u6d77\u6ca7\u533a, \u53a6\u95e8\u5e02, \u6d77\u6ca7\u533a, \u53a6\u95e8\u5e02, \u798f\u5efa\u7701, 361022, \u4e2d\u56fd", "summary_polyline": "w{mtCs_noUbCbBrE}EdCgEr@YhGjFZY|@Xrd@ld@xHjGdEfCpFrBrMdDdKdAlI@tMcB}LzAaGGiIg@oOuCwKaEyB{AgGaFsXoX", "average_heartrate": null, "average_speed": 2.9244430365426575, "streak": 3}, {"run_id": 1432071825000, "name": "run from gpx", "distance": 5004.516015643258, "moving_time": "0:27:44", "type": "Run", "start_date": "2015-05-19 21:43:45", "start_date_local": "2015-05-20 05:43:45", "location_country": "\u6ca7\u6797\u4e1c\u4e09\u8def, \u6d77\u6ca7\u533a, \u53a6\u95e8\u5e02, \u6d77\u6ca7\u533a, \u53a6\u95e8\u5e02, \u798f\u5efa\u7701, 361022, \u4e2d\u56fd", "summary_polyline": "u{mtCk_noU`BdBhA]`JmLbFrFvAa@fk@|j@rIpF`RvFrHv@|NPnNaBoN`BkGGoNiA}LoC_IaD{FaEuYkY", "average_heartrate": null, "average_speed": 3.007521644016381, "streak": 1}, {"run_id": 1432158653000, "name": "run from gpx", "distance": 5004.272816839843, "moving_time": "0:29:29", "type": "Run", "start_date": "2015-05-20 21:50:53", "start_date_local": "2015-05-21 05:50:53", "location_country": "\u6ca7\u6797\u4e1c\u4e09\u8def, \u6d77\u6ca7\u533a, \u53a6\u95e8\u5e02, \u6d77\u6ca7\u533a, \u53a6\u95e8\u5e02, \u798f\u5efa\u7701, 361022, \u4e2d\u56fd", "summary_polyline": "qzmtCk~moUv@hAf@CjF}F|AyChAe@nFjF`B[nAnBxg@vf@pLbHxOnEbNhAnIEtM}AkGnAmMX{NuAcLcCwHwCeH_Fg[sZ", "average_heartrate": null, "average_speed": 2.8288710100847045, "streak": 2}, {"run_id": 1432244739000, "name": "run from gpx", "distance": 5049.3762424529905, "moving_time": "0:29:06", "type": "Run", "start_date": "2015-05-21 21:45:39", "start_date_local": "2015-05-22 05:45:39", "location_country": "\u6ca7\u6797\u4e1c\u4e09\u8def, \u6d77\u6ca7\u533a, \u53a6\u95e8\u5e02, \u6d77\u6ca7\u533a, \u53a6\u95e8\u5e02, \u798f\u5efa\u7701, 361022, \u4e2d\u56fd", "summary_polyline": "gzmtCy_noU[`@Rd@~@l@f@K|A{BhCaBnC_F`GfFxAQzBzChe@vd@rHfFnLvEjE|@bV`BpQcBaGx@kM^_RuBkOmEwJ{Fk]y\\", "average_heartrate": null, "average_speed": 2.891968065551541, "streak": 3}, {"run_id": 1432298972000, "name": "run from gpx", "distance": 4860.2920752608325, "moving_time": "0:24:47", "type": "Run", "start_date": "2015-05-22 12:49:32", "start_date_local": "2015-05-22 20:49:32", "location_country": "\u8297\u57ce\u533a, \u4e1c\u94fa\u5934\u8857\u9053, \u8297\u57ce\u533a, \u6f33\u5dde\u5e02, \u798f\u5efa\u7701, 363005, \u4e2d\u56fd", "summary_polyline": "_irtCsi_mUnFPr@e@Hm@c@q@iFMq@hAXx@bGHJ}AeAe@{DA_@ZRvAxFR\\s@Q_AoBa@qCVWx@Pf@tEp@~@o@A_Ak@i@_EOc@ZK~@~@x@vDFf@iAu@_A_EMg@pAr@`A`EJh@mAs@iAoDOy@p@j@|AdEVf@u@Aq@o@i@aEKs@dAl@dA|DJ~@eAi@kA}DO}@hAh@hAdEJr@a@WiBkD]yA|@^|AjENn@a@YiBqD_@gAt@I`AX`@fFR`@w@e@aBwDIg@L_@|@b@hAjEPz@aAEo@q@o@wEL", "average_heartrate": null, "average_speed": 3.2685219066986098, "streak": 3}, {"run_id": 1432503379000, "name": "run from gpx", "distance": 5998.276820193484, "moving_time": "0:33:12", "type": "Run", "start_date": "2015-05-24 21:36:19", "start_date_local": "2015-05-25 05:36:19", "location_country": "\u6ca7\u6797\u4e1c\u4e09\u8def, \u6d77\u6ca7\u533a, \u53a6\u95e8\u5e02, \u6d77\u6ca7\u533a, \u53a6\u95e8\u5e02, \u798f\u5efa\u7701, 361022, \u4e2d\u56fd", "summary_polyline": "szmtCganoUe@dBf@n@lAPxFyF~AkDt@a@f@TxEdEjAS\\Vlj@tj@rGzDfP`G|KjAjJTpHQjO_C~E}AfQ}Jy@lAcGbDeNrFoLpBqLf@oSmB_PoEwMoImKyK", "average_heartrate": null, "average_speed": 3.0111831426674116, "streak": 1}, {"run_id": 1432589664000, "name": "run from gpx", "distance": 5999.214576949831, "moving_time": "0:34:37", "type": "Run", "start_date": "2015-05-25 21:34:24", "start_date_local": "2015-05-26 05:34:24", "location_country": "\u6ca7\u6797\u4e1c\u4e09\u8def, \u6d77\u6ca7\u533a, \u53a6\u95e8\u5e02, \u6d77\u6ca7\u533a, \u53a6\u95e8\u5e02, \u798f\u5efa\u7701, 361022, \u4e2d\u56fd", "summary_polyline": "oymtCsanoU}@~ATr@lA`@Pm@rF_FtCwEnFjG|@u@v@h@|]`^|PbO~PjHzOrBnNDdLiAbMcDtAsAnAUG`@kLrDeRzBoGFgJi@wKsByKkD}IuF_c@eb@", "average_heartrate": null, "average_speed": 2.8884037443186474, "streak": 2}, {"run_id": 1432676435000, "name": "run from gpx", "distance": 6041.093959705925, "moving_time": "0:35:03", "type": "Run", "start_date": "2015-05-26 21:40:35", "start_date_local": "2015-05-27 05:40:35", "location_country": "\u6ca7\u6797\u4e1c\u4e09\u8def, \u6d77\u6ca7\u533a, \u53a6\u95e8\u5e02, \u6d77\u6ca7\u533a, \u53a6\u95e8\u5e02, \u798f\u5efa\u7701, 361022, \u4e2d\u56fd", "summary_polyline": "}zmtCs_noUUd@Xh@jAb@bF_FhCyE`AYnEvElBAhBdCxf@df@lHtEfGnCnJhCdVnA|I_@lKmArCy@nIeDlAwAaDnBqPhFgO`BmGA}RkCuJ{C_HiDmF{D{]c^", "average_heartrate": null, "average_speed": 2.8726076841207444, "streak": 3}, {"run_id": 1432762347000, "name": "run from gpx", "distance": 6002.711139761298, "moving_time": "0:34:46", "type": "Run", "start_date": "2015-05-27 21:32:27", "start_date_local": "2015-05-28 05:32:27", "location_country": "\u6ca7\u6797\u4e1c\u4e09\u8def, \u6d77\u6ca7\u533a, \u53a6\u95e8\u5e02, \u6d77\u6ca7\u533a, \u53a6\u95e8\u5e02, \u798f\u5efa\u7701, 361022, \u4e2d\u56fd", "summary_polyline": "w{mtCqbnoUHhCx@v@j@AdGoFxAoDdAShF|ErA_@nOtPnZzYzIjF~L`EpLhBvN`@`MkAvH}AnMaG}LfFeLbC}Hx@}HBeLkAkHyAeFiB{LqGwHmGkVuV", "average_heartrate": null, "average_speed": 2.8776179960504784, "streak": 4}, {"run_id": 1432849069000, "name": "run from gpx", "distance": 6012.7077359951545, "moving_time": "0:35:43", "type": "Run", "start_date": "2015-05-28 21:37:49", "start_date_local": "2015-05-29 05:37:49", "location_country": "\u6ca7\u6797\u4e1c\u4e09\u8def, \u6d77\u6ca7\u533a, \u53a6\u95e8\u5e02, \u6d77\u6ca7\u533a, \u53a6\u95e8\u5e02, \u798f\u5efa\u7701, 361022, \u4e2d\u56fd", "summary_polyline": "c|mtCq_noUzBpBhGqGrCoEfG`Gb@[x@Zrl@nl@|GxDpP~E|WjBhSwClJqCrF}CgI|DoFbBuLlBiRFiO{AqSkHsKeJkWmX", "average_heartrate": null, "average_speed": 2.8057432272492555, "streak": 5}, {"run_id": 1433024991000, "name": "run from gpx", "distance": 5881.6285494388185, "moving_time": "0:33:34", "type": "Run", "start_date": "2015-05-30 22:29:51", "start_date_local": "2015-05-31 06:29:51", "location_country": "\u897f\u6865\u8857\u9053, \u8297\u57ce\u533a, \u798f\u5efa\u7701, 363005, \u4e2d\u56fd", "summary_polyline": "ukrtC}q`mUj@vCQdAPpDvBvCtBd@H`A_@vCuBd@s@|As@xI\\X`HGV{@Uk@cDc@cBb@Ip@`@v@zDP~@s@QoAaEc@eAj@`@bBvDT`Ak@g@cBiDOe@@e@r@f@jAbFPXw@_@}@gEg@q@dAp@nAfDRt@gAQ}@g@UcDG_Av@b@pAlERj@i@SoAaEc@_Ar@j@zA~DPh@k@a@}AeDc@oAj@X`B|BXrBSNi@_@{@_Eo@y@n@LvAfFh@\\aBQg@w@UyDPMpAl@f@nEJZuAy@u@gDOq@d@Il@t@~@hEHTe@KcAuAq@qCAi@nAh@x@pERn@_Ag@iAoEQs@x@j@pApEd@j@q@BeAw@o@}@E", "average_heartrate": null, "average_speed": 2.9203716730083507, "streak": 1}, {"run_id": 1433109569000, "name": "run from gpx", "distance": 6306.135783956698, "moving_time": "0:36:20", "type": "Run", "start_date": "2015-05-31 21:59:29", "start_date_local": "2015-06-01 05:59:29", "location_country": "\u6ca7\u6797\u4e1c\u4e09\u8def, \u6d77\u6ca7\u533a, \u53a6\u95e8\u5e02, \u6d77\u6ca7\u533a, \u53a6\u95e8\u5e02, \u798f\u5efa\u7701, 361022, \u4e2d\u56fd", "summary_polyline": "g{mtCi_noUbBhBPKhK_N`FzFlAOnCzBfI`J\\CrGjHpHrG|F~GbDbCnOzHhIhB~O`AfM?~PmCxH}CyN|E{OxAwQk@cLqBsLcEkGgDyi@ui@uAeA_B@gFaF", "average_heartrate": null, "average_speed": 2.8927228366773843, "streak": 2}, {"run_id": 1438290935000, "name": "run from gpx", "distance": 10019.64133797722, "moving_time": "0:56:06", "type": "Run", "start_date": "2015-07-30 21:15:35", "start_date_local": "2015-07-31 05:15:35", "location_country": "\u6ca7\u6797\u4e1c\u4e09\u8def, \u6d77\u6ca7\u533a, \u53a6\u95e8\u5e02, \u6d77\u6ca7\u533a, \u53a6\u95e8\u5e02, \u798f\u5efa\u7701, 361022, \u4e2d\u56fd", "summary_polyline": "s{mtCy~moUfB`BfFeF~D}FjFpE~ANpc@fd@jJ`IbJnExIjChPnB~KFbLwAfK}BfPaIv]eU_b@rWmRzHaO~B_GXiR_B_MqCqH}CsGkEmgA_hAiDcCyOyOiAk@Qp@dd@vd@", "average_heartrate": null, "average_speed": 2.9767205401001844, "streak": 1}, {"run_id": 1438550545000, "name": "run from gpx", "distance": 9967.80002331807, "moving_time": "0:54:52", "type": "Run", "start_date": "2015-08-02 21:22:25", "start_date_local": "2015-08-03 05:22:25", "location_country": "\u6ca7\u6797\u4e1c\u4e09\u8def, \u6d77\u6ca7\u533a, \u53a6\u95e8\u5e02, \u6d77\u6ca7\u533a, \u53a6\u95e8\u5e02, \u798f\u5efa\u7701, 361022, \u4e2d\u56fd", "summary_polyline": "ozmtCg`noUg@t@jB~AbJiLrAq@zEtEhAQp@f@ta@zb@xIjHzJnFdEvA|FlArLhAtFPrLg@lQqDxHiD`VmNnNwJwf@xZwMdFgTvCuHIyKmA{HyAqHeCmL_Hii@ci@eJyK_TsSmK}HsGkIa@\\Bh@t^h_@", "average_heartrate": null, "average_speed": 3.0278857908013577, "streak": 1}, {"run_id": 1438723728000, "name": "run from gpx", "distance": 9936.349428215099, "moving_time": "0:56:06", "type": "Run", "start_date": "2015-08-04 21:28:48", "start_date_local": "2015-08-05 05:28:48", "location_country": "\u6ca7\u6797\u4e1c\u4e09\u8def, \u6d77\u6ca7\u533a, \u53a6\u95e8\u5e02, \u6d77\u6ca7\u533a, \u53a6\u95e8\u5e02, \u798f\u5efa\u7701, 361022, \u4e2d\u56fd", "summary_polyline": "y{mtCy~moU~B`B~K_NxEpEfC\\nb@lc@`KjIhHlDfIhCrSxB`QOfSmEzXkObTiNqd@jYcNzF_HzAcMdAwHIeLaAsTmGgKeHif@kf@gHyIqCmB{QkRaIsFsJuKg@DLdAtFnE`XdY", "average_heartrate": null, "average_speed": 2.9519754688696076, "streak": 1}, {"run_id": 1438810484000, "name": "run from gpx", "distance": 10020.134730639202, "moving_time": "0:55:03", "type": "Run", "start_date": "2015-08-05 21:34:44", "start_date_local": "2015-08-06 05:34:44", "location_country": "\u6ca7\u6797\u4e1c\u4e09\u8def, \u6d77\u6ca7\u533a, \u53a6\u95e8\u5e02, \u6d77\u6ca7\u533a, \u53a6\u95e8\u5e02, \u798f\u5efa\u7701, 361022, \u4e2d\u56fd", "summary_polyline": "}{mtCo~moUzBxA|KeNbEhEh@TlAObKpLbZpY~GnF`K`FrF~AjE|@jN|@lMKzGq@nMeD|J_Fdb@iWwh@p[cJjDiNjCgJh@uQ}AmNgDmEeB_KwG_e@od@_LwMuNqM}EuFwH_GeCmD}EiEa@PN~@vGnFxB|C~RbSbA|B", "average_heartrate": null, "average_speed": 3.0336466032816234, "streak": 2}, {"run_id": 1438896957000, "name": "run from gpx", "distance": 10007.26863899918, "moving_time": "0:54:10", "type": "Run", "start_date": "2015-08-06 21:35:57", "start_date_local": "2015-08-07 05:35:57", "location_country": "\u6ca7\u6797\u4e1c\u4e09\u8def, \u6d77\u6ca7\u533a, \u53a6\u95e8\u5e02, \u6d77\u6ca7\u533a, \u53a6\u95e8\u5e02, \u798f\u5efa\u7701, 361022, \u4e2d\u56fd", "summary_polyline": "q{mtC{~moU|BtAfFsFdDgF`EzDrBTt@p@nTdUjVhUnI~ElIlChI~AhIt@bGNxI_@pGcAzJqC|V}MnVqOu`@jVkKnFkF`BmKnBkM~@gPoAmP_EmPmJqOkPgUeTiJiLgPiOu@qA}EgDuP{Pe@MMx@vb@pc@", "average_heartrate": null, "average_speed": 3.079159581230517, "streak": 3}, {"run_id": 1439415395000, "name": "run from gpx", "distance": 9971.091379961634, "moving_time": "0:56:10", "type": "Run", "start_date": "2015-08-12 21:36:35", "start_date_local": "2015-08-13 05:36:35", "location_country": "\u6ca7\u6797\u4e1c\u4e09\u8def, \u6d77\u6ca7\u533a, \u53a6\u95e8\u5e02, \u6d77\u6ca7\u533a, \u53a6\u95e8\u5e02, \u798f\u5efa\u7701, 361022, \u4e2d\u56fd", "summary_polyline": "a|mtCu~moUpBhBfFsFlBgE~Am@tDzD`C`@xc@bd@pMlKvTfHfSjBfC?tOgBlKmCjQgJl[qSif@bZyJdEoJrB{LhAeFCsLsAmP}DuOeJeQcSiXkVgDqE{E{Dw@cBec@ab@w@??x@fGnFhJvKvMrM", "average_heartrate": null, "average_speed": 2.9587808249144314, "streak": 1}, {"run_id": 1439501982000, "name": "run from gpx", "distance": 10055.370104105717, "moving_time": "0:53:24", "type": "Run", "start_date": "2015-08-13 21:39:42", "start_date_local": "2015-08-14 05:39:42", "location_country": "\u6ca7\u6797\u4e1c\u4e09\u8def, \u6d77\u6ca7\u533a, \u53a6\u95e8\u5e02, \u6d77\u6ca7\u533a, \u53a6\u95e8\u5e02, \u798f\u5efa\u7701, 361022, \u4e2d\u56fd", "summary_polyline": "m{mtCo~moUfBnAnF{FjB{DbAk@zFtFfAWld@le@hGdFrIzEpOvEdDBfEbAtI\\bIa@dPsCbR{Iv_@}UOO{`@zW_MvFiHlB_Q`CgHS}M{A{MeDgO}IcKqKkGgFmIcKyJoHyD}Dy@{BeNeM}Ae@wCiFiDcCwDcFgIgHu@CDz@lOfPvHzGpA`B^vBzChCKN", "average_heartrate": null, "average_speed": 3.138380182305155, "streak": 2}, {"run_id": 1439675837000, "name": "run from gpx", "distance": 9928.598547937963, "moving_time": "0:50:13", "type": "Run", "start_date": "2015-08-15 21:57:17", "start_date_local": "2015-08-16 05:57:17", "location_country": "\u8297\u57ce\u533a, \u4e1c\u94fa\u5934\u8857\u9053, \u8297\u57ce\u533a, \u6f33\u5dde\u5e02, \u798f\u5efa\u7701, 363005, \u4e2d\u56fd", "summary_polyline": "a`rtCwi_mUKaBaE]_A^N~AlEZn@YB_Ai@q@wDUeAn@Bz@v@f@tDLz@w@a@oAiEWcAr@b@rAfFT^u@k@uAyDQaAt@Hx@p@b@vEBTuAc@m@}EMg@nAfA~@dDN|@eAg@gAkEYy@nAb@`AfER`AeAeAkAcDQcAz@t@rAlELh@w@q@sAcEQu@h@b@xAdE\\z@}@k@qAyDS}@z@h@rA`EN|@aAaAqAuDM{@z@bAxAzDLp@iA{@iAqDKo@`@Ab@x@pAlDJp@{@w@oAcES[vAd@t@tEJb@uAu@q@}DU}@x@h@fAlE\\v@cAo@iAoEKi@bA|@hAdEDh@qAm@s@gEWy@hAh@fAnELr@mAw@cAgEIm@nAz@hApDBv@aAs@iAuEEYpA~@v@fEBb@qAeAy@aEIi@tAn@v@pEHh@g@[yAsEWq@XIp@bA|@lDNh@[Ny@kA{@wDAa@`An@bAvDPx@{@a@qA}DWgA|@Rt@l@ZhELb@oAu@{@iEEk@v@j@lA`ETh@[N_Ac@q@_FCg@hAzAz@bDFd@k@?}@q@c@sEEUlAhAx@nDH`@o@?}@uEo@{@\\", "average_heartrate": null, "average_speed": 3.295253417835368, "streak": 1}, {"run_id": 1439760452000, "name": "run from gpx", "distance": 10382.025341752023, "moving_time": "0:58:57", "type": "Run", "start_date": "2015-08-16 21:27:32", "start_date_local": "2015-08-17 05:27:32", "location_country": "\u6ca7\u6797\u4e1c\u4e09\u8def, \u6d77\u6ca7\u533a, \u53a6\u95e8\u5e02, \u6d77\u6ca7\u533a, \u53a6\u95e8\u5e02, \u798f\u5efa\u7701, 361022, \u4e2d\u56fd", "summary_polyline": "a{mtC_~moU`BlAjFeGdBmDpAm@bFbFjBN|f@jg@rJtG|ItDlIrB`T`B|O{AvQwE~j@c]_h@h[gPlFgQjBeHA{ToDeO{FwJiHkf@of@yE}Fyk@sj@g@ZH`@v^n_@lIrHNZiCzE{BpB", "average_heartrate": null, "average_speed": 2.9352630313124184, "streak": 2}, {"run_id": 1439847183000, "name": "run from gpx", "distance": 9900.20025444253, "moving_time": "0:51:49", "type": "Run", "start_date": "2015-08-17 21:33:03", "start_date_local": "2015-08-18 05:33:03", "location_country": "\u6ca7\u6797\u4e1c\u4e09\u8def, \u6d77\u6ca7\u533a, \u53a6\u95e8\u5e02, \u6d77\u6ca7\u533a, \u53a6\u95e8\u5e02, \u798f\u5efa\u7701, 361022, \u4e2d\u56fd", "summary_polyline": "m{mtCi_noUv@zAp@\\~FwGjBkDx@[`GzF`BJbd@bd@zJvHfJbEnGfBbWlC`PmAlPcEbl@o]me@hYwL`FiH|AuNzAmRoAaH{AwKuD_LiHgi@oi@eFmG{Y{W{PaQe@JFr@`RdSxEvDzDfF", "average_heartrate": null, "average_speed": 3.1843680458161887, "streak": 3}, {"run_id": 1439936400000, "name": "run from gpx", "distance": 10188.189150714961, "moving_time": "0:57:59", "type": "Run", "start_date": "2015-08-18 22:20:00", "start_date_local": "2015-08-19 06:20:00", "location_country": "\u6ca7\u6797\u4e1c\u4e09\u8def, \u6d77\u6ca7\u533a, \u53a6\u95e8\u5e02, \u6d77\u6ca7\u533a, \u53a6\u95e8\u5e02, \u798f\u5efa\u7701, 361022, \u4e2d\u56fd", "summary_polyline": "a|mtCo_noUlAbCt@BnGoI^mAtAcAbGhFt@[l@Pjg@dh@nFnDtPvGzHbBxHr@rSBtPqDxQoIl]ySRm@ga@lWmO`HoG|AyJbAePMmRoCmMcFsGgE}f@gf@wIiKoNkNs\\c[YbAdGxEbGtHxGxFfHbIN\\{@~BeCpC", "average_heartrate": null, "average_speed": 2.928482078388894, "streak": 4}, {"run_id": 1440020030000, "name": "run from gpx", "distance": 12076.505093681075, "moving_time": "1:06:04", "type": "Run", "start_date": "2015-08-19 21:33:50", "start_date_local": "2015-08-20 05:33:50", "location_country": "\u6ca7\u6797\u4e1c\u4e09\u8def, \u6d77\u6ca7\u533a, \u53a6\u95e8\u5e02, \u6d77\u6ca7\u533a, \u53a6\u95e8\u5e02, \u798f\u5efa\u7701, 361022, \u4e2d\u56fd", "summary_polyline": "s{mtCo_noUj@lAdAXtF_G|AaDz@o@`GtFpAUzd@le@vKjIdJ~DpKpCjRpA`Ke@rHcAjL_DzS_MwP`KyPzE}QnAgS}@}MiD_IuDcDaCeq@yo@fo@ln@rJlFfRhGpI|@`SNvHw@`Cs@kMlB}O?{I_AqO}DsMyGkj@gj@iC}Bd@fAc@`@", "average_heartrate": null, "average_speed": 3.0465451800406345, "streak": 5}, {"run_id": 1440105811000, "name": "run from gpx", "distance": 9976.43377859637, "moving_time": "0:53:36", "type": "Run", "start_date": "2015-08-20 21:23:31", "start_date_local": "2015-08-21 05:23:31", "location_country": "\u6ca7\u6797\u4e1c\u4e09\u8def, \u6d77\u6ca7\u533a, \u53a6\u95e8\u5e02, \u6d77\u6ca7\u533a, \u53a6\u95e8\u5e02, \u798f\u5efa\u7701, 361022, \u4e2d\u56fd", "summary_polyline": "_|mtCy~moUt@hAz@NpFyFnBmE`Aa@jEpFbBQlLlMfYnXjIjGvFvCjLpDdTjBjNi@`IcAjIcCtL}Fb`@}Vie@~YwO~FyFhAkKr@_GB}M_AsN_DsPuKaMcLkHgIqEiDc]c_@ia@g`@i@HIz@x_@|`@", "average_heartrate": null, "average_speed": 3.102124931155588, "streak": 6}, {"run_id": 1440198826000, "name": "run from gpx", "distance": 9914.268291642624, "moving_time": "0:51:38", "type": "Run", "start_date": "2015-08-21 23:13:46", "start_date_local": "2015-08-22 07:13:46", "location_country": "\u8297\u57ce\u533a, \u4e1c\u94fa\u5934\u8857\u9053, \u8297\u57ce\u533a, \u6f33\u5dde\u5e02, \u798f\u5efa\u7701, 363005, \u4e2d\u56fd", "summary_polyline": "khrtC_i_mUfFKf@y@@e@s@i@sEJ[p@`@rAhE@r@sA_Aw@uDCk@bAn@nAvDCn@a@Fw@e@o@_F?WpAh@x@`EAt@sAaAy@eDC{@~@n@rAjDBlAkAo@iAwE@]lA`@z@nECp@_Ac@_AoESu@|@n@`BpEGf@mAo@w@gEKo@`An@nAzD?l@uAaAaAsDFc@dAt@hA~D?d@kAa@y@sEIi@~@v@jA~DBh@gAu@eAyDEm@`@Ev@x@r@xDJn@{Ac@y@qEEk@|@n@tAxD@v@uAa@s@_FCa@lAb@|@lEFv@sAw@gAwDEs@XOt@r@xAjE?z@kAk@yAmEEcAbAb@bB~E@x@aBc@q@mEa@eAfADhAh@d@fED`AeAAy@m@i@kEGeAfAF~@d@^lEFp@]T}@cAuA}DEs@tAb@vA~E?n@eAYoA}EU}@^If@f@`BfFLn@qA}@yA_EIs@hAJdA`@^lE@r@iAi@uAcEUaAx@BpAh@n@lDA|@q@?eAk@y@cDEmA`@b@pCnE?z@cAA}@_@c@cFEi@lAf@~AnE@~@mBiAaAiDWy@p@GhAXv@p@ZfD?p@c@EuB", "average_heartrate": null, "average_speed": 3.20021571712157, "streak": 7}, {"run_id": 1440365028000, "name": "run from gpx", "distance": 9970.42619166949, "moving_time": "0:53:18", "type": "Run", "start_date": "2015-08-23 21:23:48", "start_date_local": "2015-08-24 05:23:48", "location_country": "\u6ca7\u6797\u4e1c\u4e09\u8def, \u6d77\u6ca7\u533a, \u53a6\u95e8\u5e02, \u6d77\u6ca7\u533a, \u53a6\u95e8\u5e02, \u798f\u5efa\u7701, 361022, \u4e2d\u56fd", "summary_polyline": "m{mtCa~moUnA`AzGuGnAoCfAk@bF~EjBKnHpIx\\f\\pL~H|LjEjJnBnJr@hOSjNgCxFqB|UsMyTlMgN~DwN`BmS}@iKoBwFqBcNqHqf@wf@kHkGzn@|m@|GpEdJ|DeGuBaGiDql@qk@", "average_heartrate": null, "average_speed": 3.1177067516164763, "streak": 1}, {"run_id": 1440451884000, "name": "run from gpx", "distance": 14789.731035509092, "moving_time": "1:21:08", "type": "Run", "start_date": "2015-08-24 21:31:24", "start_date_local": "2015-08-25 05:31:24", "location_country": "\u6ca7\u6797\u4e1c\u4e09\u8def, \u6d77\u6ca7\u533a, \u53a6\u95e8\u5e02, \u6d77\u6ca7\u533a, \u53a6\u95e8\u5e02, \u798f\u5efa\u7701, 361022, \u4e2d\u56fd", "summary_polyline": "k{mtCa_noUj@vAf@ZTOtK}MhFnFxASxk@hk@rMtHzKrC~PtA|LYdJcAnOwEjOsIqNrIcJhDsJhBcOhAeWaDaGeBeIwD{K}HsX_YwByCwLiKxq@bq@nL~FrVbFrONnLkAhKkCnYaOfU{N}m@~^qOpDsN`AqCGyMkAcJqB}PeJgl@wj@{@k@y@`@yFcFcLdMuAwA", "average_heartrate": null, "average_speed": 3.0381534584036753, "streak": 2}, {"run_id": 1440537966000, "name": "run from gpx", "distance": 9995.677355987335, "moving_time": "0:54:40", "type": "Run", "start_date": "2015-08-25 21:26:06", "start_date_local": "2015-08-26 05:26:06", "location_country": "\u6ca7\u6797\u4e1c\u4e09\u8def, \u6d77\u6ca7\u533a, \u53a6\u95e8\u5e02, \u6d77\u6ca7\u533a, \u53a6\u95e8\u5e02, \u798f\u5efa\u7701, 361022, \u4e2d\u56fd", "summary_polyline": "a|mtCs~moUjB`BnLqNxFzFhAUve@bf@`I~FrF|ClJ|CrGjAfIf@~EJfOa@fMkCnJ{DjWmPnHmD|BmBAW{WhQkOvIePpFwIz@gKHcNy@wRsFqLkHmiA_jAcTqRk@PDp@~JrIj@`BxClDjC`BnKpL", "average_heartrate": null, "average_speed": 3.047462608532724, "streak": 3}, {"run_id": 1440710851000, "name": "run from gpx", "distance": 9956.463723010056, "moving_time": "0:50:26", "type": "Run", "start_date": "2015-08-27 21:27:31", "start_date_local": "2015-08-28 05:27:31", "location_country": "\u6ca7\u6797\u4e1c\u4e09\u8def, \u6d77\u6ca7\u533a, \u53a6\u95e8\u5e02, \u6d77\u6ca7\u533a, \u53a6\u95e8\u5e02, \u798f\u5efa\u7701, 361022, \u4e2d\u56fd", "summary_polyline": "}{mtCs~moUz@fAdAFfFuFfBeDjAs@pFhF`BGfd@td@~IjHnL~ElIvBhSjBzViBbJgChL}Ff`@iVwJtFcBdBsQlJ_DhCkKlE{QdDuKPoJm@eKiBwN}EaJwGkg@og@pDtEtZlZfMvKiEeDub@mb@", "average_heartrate": null, "average_speed": 3.2903052620654516, "streak": 1}, {"run_id": 1440797960000, "name": "run from gpx", "distance": 10540.678061172153, "moving_time": "0:56:27", "type": "Run", "start_date": "2015-08-28 21:39:20", "start_date_local": "2015-08-29 05:39:20", "location_country": "\u8297\u57ce\u533a, \u4e1c\u94fa\u5934\u8857\u9053, \u8297\u57ce\u533a, \u6f33\u5dde\u5e02, \u798f\u5efa\u7701, 363005, \u4e2d\u56fd", "summary_polyline": "idrtCsq_mUnAcEqBe@_CpDIvBL^lDAEyAfAmEoB[m@PwAjDWhHhHVh@aBo@_AyEJm@jAh@rAzEFn@aCcAs@aD@s@`@UlAp@~@`FQh@qBeAm@eEDo@fA\\rAlEZvAkBu@iAsEIm@ZQz@d@jA~EXl@cC}@{@kD?_AlAt@xAvEN`@{A{@wAgE@a@~@RfA`@`@~ESLuBi@m@sAMyCj@M`Bf@j@rELj@{AWeAg@W}CC}@n@EpAv@`AhEIh@iBmA_AgECk@n@V~Al@^rDFh@c@ReA[{@iE]mAz@B`Af@n@nETl@a@ViAWs@gEk@}Ar@G`A\\r@rDXjAEL_@JiAe@s@oD_@}AfARzAlFd@jAuAe@iAu@UgEAm@zAz@hApFARyBcBe@mDEs@~@Hz@dAl@pEK^cAKs@iBm@mDRc@fAv@vA`F?j@}Aq@cAuEG{@dADt@hAf@fEBh@eBu@y@wEGm@rBz@n@tEBd@sBaBu@qDPc@dB|@r@lEAn@wAa@gAuESeArBn@z@pEFf@YPaASw@o@WaEAk@p@A|@v@z@rE?j@mA{@yAqDKyA|Av@bAhFD", "average_heartrate": null, "average_speed": 3.112098630402171, "streak": 2}, {"run_id": 1441488316000, "name": "run from gpx", "distance": 20782.192932703045, "moving_time": "2:08:06", "type": "Run", "start_date": "2015-09-05 21:25:16", "start_date_local": "2015-09-06 05:25:16", "location_country": "\u6ca7\u6797\u4e1c\u4e09\u8def, \u6d77\u6ca7\u533a, \u53a6\u95e8\u5e02, \u6d77\u6ca7\u533a, \u53a6\u95e8\u5e02, \u798f\u5efa\u7701, 361022, \u4e2d\u56fd", "summary_polyline": "q{mtC__noUtAxAd@?bKuMvFjFdBEle@|e@rHjGfSvHxQdC`MHlNoB`FuA|IuDxe@wYkg@nZkK~DqFhAkRjB_M_AuQcE}MiHgH}FiLuMkI_HwPgQvE`GaRmTkNwM_FmD_X_YqIcMiDwCfZ`^jc@za@~QxSp]t]nO`MvJrErJhCtLdAnMFvJcA|L_DzE}Bff@_Zgd@tXeHbDkHnB{RfCuMa@uIoA_LwC}LmGwj@yj@{@s@gARyFkFs@j@oA|CkGdGw@lCcDxDcBFcGy@EeAb@cAnNeQbA}B", "average_heartrate": null, "average_speed": 2.7039022811219158, "streak": 1}, {"run_id": 1441574723000, "name": "run from gpx", "distance": 11989.798709468114, "moving_time": "1:12:09", "type": "Run", "start_date": "2015-09-06 21:25:23", "start_date_local": "2015-09-07 05:25:23", "location_country": "\u6ca7\u6797\u4e1c\u4e09\u8def, \u6d77\u6ca7\u533a, \u53a6\u95e8\u5e02, \u6d77\u6ca7\u533a, \u53a6\u95e8\u5e02, \u798f\u5efa\u7701, 361022, \u4e2d\u56fd", "summary_polyline": "c|mtCi{moU`CAtKuNrFdGdAQh@Xtg@fg@rInGdD`B~NfE|KdAhKZhQ{BjIeCtFiCxe@wY}j@x\\oMrDuLvAoJJ{ToC{FiBgIkEoEcDwS}RmZuZhZn[lXjV`QnHfKhBjIj@uPuAgPwFqJmGkk@wk@\\dAQT", "average_heartrate": null, "average_speed": 2.769646271533406, "streak": 2}, {"run_id": 1441661275000, "name": "run from gpx", "distance": 10999.537652255136, "moving_time": "0:58:27", "type": "Run", "start_date": "2015-09-07 21:27:55", "start_date_local": "2015-09-08 05:27:55", "location_country": "\u6ca7\u6797\u4e1c\u4e09\u8def, \u6d77\u6ca7\u533a, \u53a6\u95e8\u5e02, \u6d77\u6ca7\u533a, \u53a6\u95e8\u5e02, \u798f\u5efa\u7701, 361022, \u4e2d\u56fd", "summary_polyline": "w{mtCy}moUrB|@hKwM`G~EtA[fBrC`YdX|GzHbOvJlR`GxPjAtNo@uJzAuJq@qN_CqM}EiMeJkk@ck@|l@zm@dJjGzNjFhPxBrILtNy@zI_CsGhBeI|@wMDcMsAeTiGaJgGoi@wh@wAL}FoFyCvEgGhG", "average_heartrate": null, "average_speed": 3.1364521392230214, "streak": 3}, {"run_id": 1441833969000, "name": "run from gpx", "distance": 10107.23480290656, "moving_time": "0:55:58", "type": "Run", "start_date": "2015-09-09 21:26:09", "start_date_local": "2015-09-10 05:26:09", "location_country": "\u6ca7\u6797\u4e1c\u4e09\u8def, \u6d77\u6ca7\u533a, \u53a6\u95e8\u5e02, \u6d77\u6ca7\u533a, \u53a6\u95e8\u5e02, \u798f\u5efa\u7701, 361022, \u4e2d\u56fd", "summary_polyline": "}zmtCo~moUrAfBtKiN~FlFfAU`@Xrj@zj@j@@bOtHtLvClIr@xMLxIw@|LiCtL{Fna@{V{i@|[kLnDyGfAgJbAqGGiKmAkL{C}FkBsFeDgEeDgd@yc@uUkWqKuJeBk@eQuQ_@b@NZnHrH|Az@nUxV}@zBiB~A", "average_heartrate": null, "average_speed": 3.009897201580274, "streak": 1}, {"run_id": 1441919101000, "name": "run from gpx", "distance": 12371.830039126957, "moving_time": "1:08:31", "type": "Run", "start_date": "2015-09-10 21:05:01", "start_date_local": "2015-09-11 05:05:01", "location_country": "\u6ca7\u6797\u4e1c\u4e09\u8def, \u6d77\u6ca7\u533a, \u53a6\u95e8\u5e02, \u6d77\u6ca7\u533a, \u53a6\u95e8\u5e02, \u798f\u5efa\u7701, 361022, \u4e2d\u56fd", "summary_polyline": "_|mtCw~moUnBzA|K{MnFbF~AGjg@|g@tHpFbPpGpGdA~PjAbIS|IeAjP_F`g@kZj@_A_N|JcXnOuRpG}Kx@qJGoOmAuJiCqNwHoGuFo`@i`@gK}L_ViUaDsByMcNmMqN_CoE_CkCwOkMe@JpErBpItH|RpVfQpQdAzCpVxV_ChFkFpF", "average_heartrate": null, "average_speed": 3.009445399933582, "streak": 2}, {"run_id": 1442009566000, "name": "run from gpx", "distance": 10029.292788377363, "moving_time": "0:50:30", "type": "Run", "start_date": "2015-09-11 22:12:46", "start_date_local": "2015-09-12 06:12:46", "location_country": "\u8297\u57ce\u533a, \u4e1c\u94fa\u5934\u8857\u9053, \u8297\u57ce\u533a, \u6f33\u5dde\u5e02, \u798f\u5efa\u7701, 363005, \u4e2d\u56fd", "summary_polyline": "yfrtCoi_mUrDJz@cAs@kAkEE}@~@~@nAtEFf@aAi@cAyFCYhAfA|@lE@f@qAo@_AwEGw@|@V`At@XlE@\\sA_A}@sEEe@f@Dp@lAz@hE@Zm@G}@i@c@iF?_@f@Jt@jAj@tDHj@k@Bw@eAq@wEBa@dAdB`AtDDh@o@Cu@i@i@sFEg@|@nAnAtDPr@e@DcAy@u@gEMu@rAlAnAfDLl@k@DaAgAs@kEBUjAbBlArDG^{AgA{@iE@c@h@?r@nAl@rDPp@s@A{@m@i@{EKs@dAnAnAbEFd@g@@}@q@m@wEEe@tAz@~@vE?^k@KeAcAa@uDCw@nA`@x@z@TnD@h@q@IaAs@e@eFBSz@`AtAbEHn@gAS_Ay@[gENY~@Xz@xCVdA?r@e@G{AuEi@aAb@Cz@b@n@fEXdAu@[{AqEYiAj@`@dBpD^t@Kb@w@i@yAoEUk@j@CbAf@p@tDL~@w@MqAsEc@_At@^zAzEXv@oAs@qAaEKi@VMv@z@jAzDPp@oA}@kAyDOm@b@Oz@l@t@fETbAgAq@yAeEQu@lAp@vAdDNpAs@a@gBeESmA|@z@zAfELt@yAk@{@", "average_heartrate": null, "average_speed": 3.309997619926522, "streak": 3}, {"run_id": 1442178420000, "name": "run from gpx", "distance": 12354.618749445988, "moving_time": "1:07:56", "type": "Run", "start_date": "2015-09-13 21:07:00", "start_date_local": "2015-09-14 05:07:00", "location_country": "\u6ca7\u6797\u4e1c\u4e09\u8def, \u6d77\u6ca7\u533a, \u53a6\u95e8\u5e02, \u6d77\u6ca7\u533a, \u53a6\u95e8\u5e02, \u798f\u5efa\u7701, 361022, \u4e2d\u56fd", "summary_polyline": "e{mtCo}moU^A`AdAzKqNvEpEl@Zt@]f@^dGbHlc@zb@nS~I|FjAxNdAfIL|Ge@nQgE`K_Fta@qW}MfJuFfCcRdLgOzEqU~BmQcB}LsCqKgFyGiFebAgcAqF{DcOmOsVwZwGyFsGwDjGvD~FlFdU|XxMrMdBvEdWxVLTaDjFkDtD", "average_heartrate": null, "average_speed": 3.0310644625726173, "streak": 1}, {"run_id": 1442264540000, "name": "run from gpx", "distance": 10558.2365825866, "moving_time": "0:58:51", "type": "Run", "start_date": "2015-09-14 21:02:20", "start_date_local": "2015-09-15 05:02:20", "location_country": "\u6ca7\u6797\u4e1c\u4e09\u8def, \u6d77\u6ca7\u533a, \u53a6\u95e8\u5e02, \u6d77\u6ca7\u533a, \u53a6\u95e8\u5e02, \u798f\u5efa\u7701, 361022, \u4e2d\u56fd", "summary_polyline": "g{mtCm~moU`B~AnKsN`GxFl@g@C]iRyS{YoWmOiPqKiOkMkJdLzIbMjOvA|CvBrAjDvElDjCjDlE|MpKhJnKzExDrHfJf`@z_@~EfG|GpEnHpCpLbCpNfAzRg@lIqAZe@_LdCuJt@iQkA{HwAsMsE}HmFqi@{h@mBYoF{E_KlL", "average_heartrate": null, "average_speed": 2.9901547954082695, "streak": 2}, {"run_id": 1442352219000, "name": "run from gpx", "distance": 13814.440127368278, "moving_time": "1:15:04", "type": "Run", "start_date": "2015-09-15 21:23:39", "start_date_local": "2015-09-16 05:23:39", "location_country": "\u6ca7\u6797\u4e1c\u4e09\u8def, \u6d77\u6ca7\u533a, \u53a6\u95e8\u5e02, \u6d77\u6ca7\u533a, \u53a6\u95e8\u5e02, \u798f\u5efa\u7701, 361022, \u4e2d\u56fd", "summary_polyline": "u}mtC{_noU~CjCxGkIfAiCdAGvFvEjBJpi@ni@pHvEjOhFvJbBlJl@pSuAdLoC}GxBaInAoIt@{JWoPsCoPoGmHcGol@kl@hi@vh@dHbGlOnHjIvBnGv@jIl@zLYnPyChJoDjf@uZgAlAw_@rUuLnFyE~AoK|AaPDaRcCwPgGwIeGqg@uf@gBSqFaFqJ~K", "average_heartrate": 155.0, "average_speed": 3.0671492289894045, "streak": 3}, {"run_id": 1442439176000, "name": "run from gpx", "distance": 5517.0710485595555, "moving_time": "0:30:49", "type": "Run", "start_date": "2015-09-16 21:32:56", "start_date_local": "2015-09-17 05:32:56", "location_country": "\u6ca7\u6797\u4e1c\u4e09\u8def, \u6d77\u6ca7\u533a, \u53a6\u95e8\u5e02, \u6d77\u6ca7\u533a, \u53a6\u95e8\u5e02, \u798f\u5efa\u7701, 361022, \u4e2d\u56fd", "summary_polyline": "a|mtCe~moUtB~AnKmNfGhFt@g@`@Ppi@ti@jJ`GfKxDfGlA|OpAhGQXYJiA{@We@Dk@`AmAPqHSm@b@sHm@sEy@cMuEgLoI_a@ca@wCeCyBm@oEkE{@PkChEsEzE", "average_heartrate": 149.0, "average_speed": 2.983813438918094, "streak": 4}, {"run_id": 1442524836000, "name": "run from gpx", "distance": 13878.462409535652, "moving_time": "1:14:56", "type": "Run", "start_date": "2015-09-17 21:20:36", "start_date_local": "2015-09-18 05:20:36", "location_country": "\u6ca7\u6797\u4e1c\u4e09\u8def, \u6d77\u6ca7\u533a, \u53a6\u95e8\u5e02, \u6d77\u6ca7\u533a, \u53a6\u95e8\u5e02, \u798f\u5efa\u7701, 361022, \u4e2d\u56fd", "summary_polyline": "k|mtCc_noUbCnBbGsGbCuEjGjFzAKth@xh@dNnInOtE`QnA`Po@pGaAfJyCyGfCsJbB}Iv@wFIoJy@eKqBkNoFeEqCkp@ip@h^f^vTvRdFvC|GxBzNbDzJn@vC[xIFfM_CxKeEnf@_Zs_@vUsIrEaHbC_OdCkOFqReCgIiCiJmE}GcFyc@qd@_Am@oBM}EqEmCbEyE`F", "average_heartrate": 151.0, "average_speed": 3.086846621338001, "streak": 5}, {"run_id": 1442615023000, "name": "run from gpx", "distance": 9957.036931399292, "moving_time": "0:50:39", "type": "Run", "start_date": "2015-09-18 22:23:43", "start_date_local": "2015-09-19 06:23:43", "location_country": "\u8297\u57ce\u533a, \u4e1c\u94fa\u5934\u8857\u9053, \u8297\u57ce\u533a, \u6f33\u5dde\u5e02, \u798f\u5efa\u7701, 363005, \u4e2d\u56fd", "summary_polyline": "qhrtCuh_mUfFDr@cAAg@w@s@iE@g@`AHh@dBn@tC?b@oBq@q@cE?s@z@VlA^P`ELb@a@JqA{@q@kEBa@hAf@bA`ERb@M^iAe@cAcEO}@l@f@fBdENt@gAc@gAyEO]\\CjA`Al@|CLd@OZoAo@_AcEGq@v@RlA^RhEBf@mAi@cAiFBOlAhAz@|DCVyAs@s@wE?]fApAhA|DC^iAk@gAgEGw@t@Ah@p@z@fEHn@s@?{@{@q@gE@g@`AFj@`Aj@~D?d@gAa@iAeEQc@Jc@hAh@bA~DPd@I^iAc@gAyEKo@x@?h@v@v@`EFp@}@Cm@u@u@yDAs@pAb@`AfEJt@u@@k@q@y@aECq@z@p@|AdEFn@y@YqAa@OgEBc@`Af@fA`EJx@s@KoA_@SeE?m@`Ab@bAfELt@wAs@}@gE@e@fAj@bAdEHn@aA[mAa@MoDG_@PSpAt@v@fEBd@eAe@kAgE?s@f@Ch@n@z@fEJn@_ACm@{@s@aEDi@dAh@dAhENt@{@Ai@s@w@sD?{@t@ThA`@PvDHt@mAg@aA}EE_@dAr@fA|DHv@gA]eAa@KyDCo@jAh@`A|DNz@m@OsAcBYkCDc@ZClA", "average_heartrate": 163.0, "average_speed": 3.2764188652185893, "streak": 6}, {"run_id": 1442741945000, "name": "run from gpx", "distance": 21145.26364686594, "moving_time": "1:58:23", "type": "Run", "start_date": "2015-09-20 09:39:05", "start_date_local": "2015-09-20 17:39:05", "location_country": "\u6ca7\u6797\u4e1c\u4e09\u8def, \u6d77\u6ca7\u533a, \u53a6\u95e8\u5e02, \u6d77\u6ca7\u533a, \u53a6\u95e8\u5e02, \u798f\u5efa\u7701, 361022, \u4e2d\u56fd", "summary_polyline": "g{mtCybnoUErBp@~@hA`@bFiG|BeEb@G`GjFb@c@r@Zre@`f@hIlG|PnHhP~BdKPxDq@nEEfPiDvMsGb`@sUsl@`]gGvByFfAiTlBuOuBaKiCsJiE}IuG_fA_gA{FeE}UkVmLoPaGqFwGiD|EbCbG~EtU`YpRnR|DpCrK`Lv@nBzC~AzNlPpa@ja@tHnFpJhEhKjCnPbAjRq@dEu@xOuFbg@mZma@dWeSrIuGnAoJx@mAWaFLoN{A{QmFcMiImhAihAaA_@mQgQc@VDZrKfK", "average_heartrate": 160.0, "average_speed": 2.97694828197465, "streak": 7}, {"run_id": 1442837094000, "name": "run from gpx", "distance": 8388.689160422857, "moving_time": "0:46:50", "type": "Run", "start_date": "2015-09-21 12:04:54", "start_date_local": "2015-09-21 20:04:54", "location_country": "\u6ca7\u6797\u4e1c\u4e09\u8def, \u6d77\u6ca7\u533a, \u53a6\u95e8\u5e02, \u6d77\u6ca7\u533a, \u53a6\u95e8\u5e02, \u798f\u5efa\u7701, 361022, \u4e2d\u56fd", "summary_polyline": "y{mtCc_noUtAbB\\?zEgFxBgEx@m@tFtFv@i@x@f@|d@ve@zKpHdGrCbJnCtRpBzPo@tO{CzIcEbe@eYwf@`ZeKbEcFpAoGp@}QZ}OkBoMyD{CaBeLcJyd@wd@_BLcFyE_@CmGfJkBrA", "average_heartrate": 151.0, "average_speed": 2.98529863360244, "streak": 8}, {"run_id": 1442870669000, "name": "run from gpx", "distance": 5153.690632984471, "moving_time": "0:33:31", "type": "Run", "start_date": "2015-09-21 21:24:29", "start_date_local": "2015-09-22 05:24:29", "location_country": "\u6ca7\u6797\u4e1c\u4e09\u8def, \u6d77\u6ca7\u533a, \u53a6\u95e8\u5e02, \u6d77\u6ca7\u533a, \u53a6\u95e8\u5e02, \u798f\u5efa\u7701, 361022, \u4e2d\u56fd", "summary_polyline": "y{mtC_~moUjBxAb@SdGcHrAqCt@QhFzEn@g@b@Vjb@jb@rK`JdJzEbH~BrS~BkMgAgHaByK}D}ImGom@sm@zB~Bg@n@{FmFuGnI", "average_heartrate": 128.0, "average_speed": 2.5627501904447896, "streak": 9}, {"run_id": 1442957347000, "name": "run from gpx", "distance": 10089.346574162582, "moving_time": "0:50:43", "type": "Run", "start_date": "2015-09-22 21:29:07", "start_date_local": "2015-09-23 05:29:07", "location_country": "\u6ca7\u6797\u4e1c\u4e09\u8def, \u6d77\u6ca7\u533a, \u53a6\u95e8\u5e02, \u6d77\u6ca7\u533a, \u53a6\u95e8\u5e02, \u798f\u5efa\u7701, 361022, \u4e2d\u56fd", "summary_polyline": "cxmtC_|moUzFcGlCkEpGxEx@a@ZTdd@zd@zOfLnOlFrThBjGKxOoB|OoFxe@yYNmAiDiFFaCr@p@@bAbCjGkAtAs_@rUuH~D_HbC{M|BcKd@iNw@oHuAyFmBkHaD}FcE{}Aa}Ay@e@[^Pd@lUbU", "average_heartrate": 159.0, "average_speed": 3.3155920388309505, "streak": 10}, {"run_id": 1443043809000, "name": "run from gpx", "distance": 12947.04933120273, "moving_time": "1:14:10", "type": "Run", "start_date": "2015-09-23 21:30:09", "start_date_local": "2015-09-24 05:30:09", "location_country": "\u6ca7\u6797\u4e1c\u4e09\u8def, \u6d77\u6ca7\u533a, \u53a6\u95e8\u5e02, \u6d77\u6ca7\u533a, \u53a6\u95e8\u5e02, \u798f\u5efa\u7701, 361022, \u4e2d\u56fd", "summary_polyline": "_|mtCa~moUxBxA`K{M^DdFtE~AI|d@~d@zJ|HnG|CdIlCpRfBoLs@mTmG}HeFgo@uo@|l@jl@tJrHtOpFzHrA|Jt@vNm@a@XaEZmDKP[zDR`ESnHiAbIyBzL_Gn`@qVgY|QaRzJkIfCeRtB_HB}PmBuRgHwL}I{b@sc@eAg@aBFqFsFoCtEwFzFYRw@y@", "average_heartrate": 152.0, "average_speed": 2.909449287910726, "streak": 11}, {"run_id": 1443130412000, "name": "run from gpx", "distance": 11369.457395685451, "moving_time": "1:02:54", "type": "Run", "start_date": "2015-09-24 21:33:32", "start_date_local": "2015-09-25 05:33:32", "location_country": "\u6ca7\u6797\u4e1c\u4e09\u8def, \u6d77\u6ca7\u533a, \u53a6\u95e8\u5e02, \u6d77\u6ca7\u533a, \u53a6\u95e8\u5e02, \u798f\u5efa\u7701, 361022, \u4e2d\u56fd", "summary_polyline": "{{mtC_~moUxBlAvJsMf@@lFfErAGvj@bk@fDbC~HjD}HiEsEsDon@im@`h@~g@bP~LnErBvLvCxPbBhMYhHy@fIuBbIiDxe@yY}a@jWeI`EgGtBqHrAiPnAaU{BiIcCwHwDeKmHc^m]yDwEwAs@iADcFcFi@P}BvD_GtGa@]", "average_heartrate": 148.0, "average_speed": 3.0125748266257157, "streak": 12}, {"run_id": 1443221270000, "name": "run from gpx", "distance": 9871.876376401606, "moving_time": "0:48:04", "type": "Run", "start_date": "2015-09-25 22:47:50", "start_date_local": "2015-09-26 06:47:50", "location_country": "\u8297\u57ce\u533a, \u4e1c\u94fa\u5934\u8857\u9053, \u8297\u57ce\u533a, \u6f33\u5dde\u5e02, \u798f\u5efa\u7701, 363005, \u4e2d\u56fd", "summary_polyline": "qhrtCwh_mU|E?x@q@CgA_@YkDM_AZOf@\\jA~DV~@_@Hg@k@eAyCOkALWb@TlAzDVnAo@MkA_@W_EGq@x@VfAbFNh@_Ac@eAgEOy@r@PlA`@RbEBp@}@c@gAkEQy@l@JpA^RbEHp@y@SmAa@QaE@m@v@x@vAbE@h@_A]kA_EUe@He@dAd@`AxETh@aAEk@_Ak@_EB]hAj@~@|DH`@OXkAw@{@{DK_@TOpAx@t@~DAf@eA{@kA}DEm@z@Bh@z@n@`E?f@gAg@aA{DO_Ah@Gj@j@~@`EJv@s@Bg@s@{@_ECs@x@j@vAtE@d@gAi@eA_EE{@p@Ad@l@x@`EHr@u@@e@s@w@eEEk@~@^fAdFHb@mAm@{@aEEw@p@@h@x@r@xDF^SNqA{@o@aEAk@~@Hh@`Af@~DA^iAo@}@uEIc@jAJf@`A^lDDj@}@Ei@{@k@{DC]XClA|@j@zD?b@yAu@s@_EAq@~@p@nAlE?f@_Ae@eAeEGy@t@t@vAnEI\\iAo@{@kEAk@~@Bf@|@j@rDAt@s@Cm@cAu@yDDc@pAp@|@|D?t@w@Ek@{@m@cEL[XHnAnBZpCMTmAUe@yCSkB\\?vA~B`@", "average_heartrate": 168.0, "average_speed": 3.4229807130380046, "streak": 13}, {"run_id": 1443389576000, "name": "run from gpx", "distance": 14632.215098806135, "moving_time": "1:14:34", "type": "Run", "start_date": "2015-09-27 21:32:56", "start_date_local": "2015-09-28 05:32:56", "location_country": "\u897f\u6865\u8857\u9053, \u8297\u57ce\u533a, \u798f\u5efa\u7701, 363005, \u4e2d\u56fd", "summary_polyline": "kkrtCis`mUhJ~B|Jd@zHc@tCx@dBwLtAaDxBsKnHgLdLiUlGcVxBwBzIkNnEeJhF{GlV}Wn@uBzA}UaBaST{BpAyAB_B[q@eBAcD{OmG}QyAaHwJmP]wB_BgDgBw@aB{DfBeF@mD_AoDgAgB@iDs@eB~A_WvBeCVsAyBaKiEvw@DhDtCvLvOdYfE~O`FdK~@~CfCvR`CzY?vE{@dHeBjG{CpFUpA{TjXkUnb@sA~D}@l@}AnGoAc@c@\\w@bEyFvK_CjDyBbBiDzHg@`DaBlCcCnI}AdCa@PoHcBaRg@", "average_heartrate": 155.0, "average_speed": 3.2704995750572494, "streak": 1}, {"run_id": 1443476717000, "name": "run from gpx", "distance": 6827.29630247781, "moving_time": "0:36:43", "type": "Run", "start_date": "2015-09-28 21:45:17", "start_date_local": "2015-09-29 05:45:17", "location_country": "\u6d77\u6ca7\u533a, \u53a6\u95e8\u5e02, \u5d69\u5c7f\u8857\u9053, \u53a6\u95e8\u5e02, \u798f\u5efa\u7701, 361022, \u4e2d\u56fd", "summary_polyline": "aamtCmdnoUnm@ll@~IpF|HrCzFjAlH|@vINfU_CtLoDzSmMqOjKoLlEuHvAoNtAcPeAgF}@aPaFmOgLie@id@mBGaFyEa@BeCpE{F~F", "average_heartrate": 150.0, "average_speed": 3.0990904686690013, "streak": 2}, {"run_id": 1443531673000, "name": "run from gpx", "distance": 21258.857055837023, "moving_time": "1:51:35", "type": "Run", "start_date": "2015-09-29 13:01:13", "start_date_local": "2015-09-29 21:01:13", "location_country": "\u6ca7\u6797\u4e1c\u4e09\u8def, \u6d77\u6ca7\u533a, \u53a6\u95e8\u5e02, \u6d77\u6ca7\u533a, \u53a6\u95e8\u5e02, \u798f\u5efa\u7701, 361022, \u4e2d\u56fd", "summary_polyline": "aymtCq}moUn@|A^Hj@k@LmB|@k@dDeG~@g@xFzEnAm@d@dAle@~d@rLtIzInDbHhB`RzAlRsAtNkDxKqFjSmMfMwGxDrExCrI`@jEE~DtBzWo@`Aw]dEgkAvVocAvFiEl@_b@nA{DsCmAYoWoSk@kNeAyFqA[uIl@cHvEyIeM}AoAw@mBFe@vBiBxEaCfn@mDh@}AAyFeA}JAuEyIg@}IkCSkAjA}DnY_^lBaEg@cAwR{RaE_DeKePqO_L}IqD{I_A}HbAoIlFcNpNq]jSyD|AcE~CrEgDha@kUjUmSnIyCzHAzDr@xFvBjOrKrUbYxPxPx@~CbJlJ", "average_heartrate": 153.0, "average_speed": 3.1753333914618405, "streak": 2}, {"run_id": 1443651590000, "name": "run from gpx", "distance": 9816.607574468806, "moving_time": "0:57:26", "type": "Run", "start_date": "2015-09-30 22:19:50", "start_date_local": "2015-10-01 06:19:50", "location_country": "\u897f\u6865\u8857\u9053, \u8297\u57ce\u533a, \u798f\u5efa\u7701, 363005, \u4e2d\u56fd", "summary_polyline": "ojrtC}o`mUNjKfE~@t@xBc@nCuBp@_BnCSjHHTjGPt@_@HaAk@{@_EMs@x@LnA^VbEDn@cBk@y@aEAq@x@RnA`@N`EBh@cA[iAa@Q}DJe@`Af@bA`ELp@_AEk@y@m@yC?c@Ha@hAn@z@|DFp@i@Bk@m@{@yDG{@p@Ah@t@x@`EAj@_A]iAeFB_@fAn@|@`EFr@y@?g@u@s@eEAg@dAh@dA`ELp@y@MkAa@SkDE{@n@LnA`@TfE?d@gAi@aAgEAm@z@^fAdENv@w@OmAc@S}D@o@z@Bh@p@h@|D?n@}@[gAaEM_Aj@HlA^T|D@t@{@]iAa@K{DDe@bA`@bAzE@d@iAk@_A}DKw@l@HjAZV`EN^QRmAq@u@}DAk@`Ab@bA~DLv@m@Bi@q@w@{DGu@jAd@`AxDLb@I`@eAm@cA}DGw@p@LlA`@PhEDh@eAGe@}@i@_DFs@d@Gd@h@t@jECd@cAw@{@}DDg@`Af@bA`EEt@y@a@gA}DI}@j@Eh@r@x@|D?p@w@e@mAiECq@x@^dAxEJf@gAg@aA_EGq@v@XdA~DTx@k@OoA_@QkDAy@p@VlA`FHb@y@", "average_heartrate": 148.0, "average_speed": 2.8486963361778312, "streak": 1}, {"run_id": 1443774653000, "name": "run from gpx", "distance": 9797.639533043179, "moving_time": "0:51:33", "type": "Run", "start_date": "2015-10-02 08:30:53", "start_date_local": "2015-10-02 16:30:53", "location_country": "\u8297\u57ce\u533a, \u4e1c\u94fa\u5934\u8857\u9053, \u8297\u57ce\u533a, \u6f33\u5dde\u5e02, \u798f\u5efa\u7701, 363005, \u4e2d\u56fd", "summary_polyline": "ihrtCwi_mUrE^t@iAc@cAaFIe@n@@j@j@n@nEDn@aA_@eAg@McDIe@LYhAn@~@bEJb@SN}@i@}@cEMe@ROlAz@p@bEFd@eAk@gAeEUa@RSjAn@z@fED^UHmAw@o@yDK_@TOlAx@r@`EBh@eAk@aA_EEy@n@@j@~@n@`E?`@gAm@aAgEGq@z@Bh@|@n@xD@j@cAg@gA_EU}@n@NpA^T|DLp@u@_@yAiESu@x@VnAb@NxDJn@{@q@wAcEKq@x@VnAb@P|D?r@}@YkAaGAYjALb@dAZ~DAX_@CoAaAc@_E@]x@Jd@|@j@~DAXoAy@w@cE?e@dAj@`A~DHr@w@[qAaE[cA|An@`AtDHb@OZkAa@u@gEOu@r@LlA^PbEFn@{@Ci@y@m@}DGU^FtAz@j@|CA^WPqA}@m@qDYc@bALrA`@PzCFb@M`@gAm@}@_EOa@PSvAt@n@`E@h@eAe@cAwDSw@t@@nA^RrEDf@iAi@aAaEWw@|@PlA^RbEBh@eAi@eAuEG_@fA`@bAdEDp@}@c@iA}DOe@ZGpA`Ad@~CF`@YHmAaAi@wCGe@RSrAx@j@tDBd@eAIe@eAg@mDFYpAdAz@", "average_heartrate": 158.0, "average_speed": 3.1676817112975035, "streak": 2}, {"run_id": 1443824082000, "name": "run from gpx", "distance": 9818.675599234934, "moving_time": "0:53:25", "type": "Run", "start_date": "2015-10-02 22:14:42", "start_date_local": "2015-10-03 06:14:42", "location_country": "\u8297\u57ce\u533a, \u4e1c\u94fa\u5934\u8857\u9053, \u8297\u57ce\u533a, \u6f33\u5dde\u5e02, \u798f\u5efa\u7701, 363005, \u4e2d\u56fd", "summary_polyline": "ihrtCsh_mUbEDf@Ib@y@c@sAeEKc@PSnAv@r@nDFz@q@MoAa@UeEI_@RMdAt@z@fEBd@m@SoAa@SqDM{@lAZ`AxERl@{@YmAa@M{DCk@`A\\fAbERh@MXs@k@qAiEG_@RKnAz@n@~D@d@aAa@eAe@KqD@m@z@`@jAtEJp@{@]iA}EOk@|@\\fAd@JbEE\\iAaAaA_DA_An@`@zAnEPp@w@?g@w@{@oDKy@j@Cf@r@hA~DF`@WJkAu@q@iE?_@bAd@bA|EB^eAu@cAiEG_@XCjAx@n@`ECb@gAm@aAaEKq@p@?l@x@z@zDAh@uA{@y@eE@e@fAv@bArDHb@OXiAs@}@cEGm@t@@j@n@n@~DHb@SLmAy@u@cEEe@t@Dt@|@j@~CFd@K\\gAq@_A{E@WjAr@x@hED\\]?kAcAe@}DHWjAt@t@dEBf@eAm@aAiEK_@VIlA~@j@|DA\\eAq@}@cEAa@V@rA`A^|C?v@q@Ai@}@q@iE?[fAr@z@hE?f@aAk@_AaEIw@t@Bj@z@j@dEC^cAo@}@}DGu@t@VjA`@JdEAb@gAq@{@{E@YhAr@z@`E@b@SJmA{@i@_EA_@REnAp@d@fA@", "average_heartrate": 149.0, "average_speed": 3.0635493289344566, "streak": 3}, {"run_id": 1444132773000, "name": "run from gpx", "distance": 10764.131965384184, "moving_time": "0:59:17", "type": "Run", "start_date": "2015-10-06 11:59:33", "start_date_local": "2015-10-06 19:59:33", "location_country": "\u8297\u57ce\u533a, \u4e1c\u94fa\u5934\u8857\u9053, \u8297\u57ce\u533a, \u6f33\u5dde\u5e02, \u798f\u5efa\u7701, 363005, \u4e2d\u56fd", "summary_polyline": "}hrtC{h_mUhEJdA_@FoAY]kCYgBj@GnA\\ZnEJ^WDqAWa@_EQc@Hc@bAf@|@|DHx@k@OuA{DSkAnAj@|@bEDh@}@Eg@{@m@{DBc@bAt@`A|DDp@{@Ii@aAe@wD@c@dAv@|@`EHh@aAg@cAeEMm@|@f@fA`EHl@w@e@mAiDOaAb@R|A~D\\dA{@o@uAsDGo@XEf@`@bAxDNx@o@?i@u@w@{CAgAl@XlA`@L~DD`@{@g@gAcEM{@bAd@fA~DLv@m@@e@s@{@aEEe@dAn@~@fEFb@iAs@aAeE@c@bAp@~@~DFh@{@c@cAuEI[`Aj@z@fDJz@k@Bk@u@u@qDEo@x@d@lAnEJd@_Ac@gAgEMo@lAj@|@dEJl@cAc@aAgEWs@|@`@jAbENt@y@a@kAcEOw@t@Bh@|@p@~CFz@aAc@gAcEQu@v@^nA`ERx@o@@k@w@w@_DG}@f@Gj@n@x@dEDh@cAm@aAcEKi@j@@j@r@v@`EBb@eAo@_A_EGo@~@d@`A~DLt@y@YgAwD[e@Fe@jAj@`A~DHl@a@Hi@o@_A_DOc@Dk@`Ab@dA|CNhASNg@_@kAyC[mAVSnARd@bER~@i@Bm@s@{@}CKiAp@LpAfFVd@iAOg@iBa@sB?m@`ABd@`Aj@~C@t@{@Ai@aAk@}DF[fA|A`AfDK", "average_heartrate": 155.0, "average_speed": 3.026182728530836, "streak": 1}, {"run_id": 1444305524000, "name": "run from gpx", "distance": 11134.620151741414, "moving_time": "0:58:41", "type": "Run", "start_date": "2015-10-08 11:58:44", "start_date_local": "2015-10-08 19:58:44", "location_country": "\u6ca7\u6797\u4e1c\u4e09\u8def, \u6d77\u6ca7\u533a, \u53a6\u95e8\u5e02, \u6d77\u6ca7\u533a, \u53a6\u95e8\u5e02, \u798f\u5efa\u7701, 361022, \u4e2d\u56fd", "summary_polyline": "i{mtCc_noUtAdB|@a@pEsEpAaDpA}@tExE`BIxm@dl@jFbD~GnCrQpDlH\\bKQhRyCdJmDng@eZfBb@`B|B~C`Kr@fLSjAwDt@mRnAw@`Dd@vQU`@}F|AuGz@oWrGyd@lJ{p@|DkBCa@e@q@eHLiCo@aAs_@bB_@c@y@cJm@uBsAcBcCwAuC[}Dp@oBrAmAwBq@gDyBge@qAwCM}FrA}GjImK", "average_heartrate": 155.0, "average_speed": 3.1623459675493932, "streak": 1}, {"run_id": 1444339813000, "name": "run from gpx", "distance": 13274.784609656614, "moving_time": "1:12:08", "type": "Run", "start_date": "2015-10-08 21:30:13", "start_date_local": "2015-10-09 05:30:13", "location_country": "\u6ca7\u6797\u4e1c\u4e09\u8def, \u6d77\u6ca7\u533a, \u53a6\u95e8\u5e02, \u6d77\u6ca7\u533a, \u53a6\u95e8\u5e02, \u798f\u5efa\u7701, 361022, \u4e2d\u56fd", "summary_polyline": "a|mtCq~moUj@xA|AEvCcCCa@pEaG`Aa@zErErA@rChCfd@~c@~KjHvJrD~JnBbOn@tO}@yP`BgSsBuJkCwGwCeMgJyj@uj@hf@pf@~LbKzQ`IhPfC`LT~Kw@jI_BlMcF`f@}Yqf@dZqJ`EwQdDeK\\cL{@oHuAqOyF}KaI}e@{e@iBCcFcFuAd@cB|CuFzF", "average_heartrate": 156.0, "average_speed": 3.0671868321757425, "streak": 2}, {"run_id": 1444425827000, "name": "run from gpx", "distance": 8344.574213633125, "moving_time": "0:45:59", "type": "Run", "start_date": "2015-10-09 21:23:47", "start_date_local": "2015-10-10 05:23:47", "location_country": "\u6ca7\u6797\u4e1c\u4e09\u8def, \u6d77\u6ca7\u533a, \u53a6\u95e8\u5e02, \u6d77\u6ca7\u533a, \u53a6\u95e8\u5e02, \u798f\u5efa\u7701, 361022, \u4e2d\u56fd", "summary_polyline": "c|mtCi}moUz@t@bA?dFiG~BmE|@AlF~E~AUxe@rf@~ItGnP~GdP~BpLLzF]xOwCzJuDdf@iZaf@`ZwFdCgNpDySrAsJw@yMoCuEcBsJoFwFmE_d@id@_CU_GyFyC~EqF`G", "average_heartrate": 145.0, "average_speed": 3.024492284752854, "streak": 3}, {"run_id": 1444461804000, "name": "run from gpx", "distance": 3432.0934759962265, "moving_time": "0:13:43", "type": "Run", "start_date": "2015-10-10 07:23:24", "start_date_local": "2015-10-10 15:23:24", "location_country": "\u6d77\u6ca7\u533a, \u53a6\u95e8\u5e02, \u5d69\u5c7f\u8857\u9053, \u53a6\u95e8\u5e02, \u798f\u5efa\u7701, 361022, \u4e2d\u56fd", "summary_polyline": "eygtC}imoUwMzIoY~OcOtD}OzAiT{BqFqA}LwEeNyKs`@ya@", "average_heartrate": 178.0, "average_speed": 4.170222935596873, "streak": 3}, {"run_id": 1444512301000, "name": "run from gpx", "distance": 12806.060256843888, "moving_time": "1:25:30", "type": "Run", "start_date": "2015-10-10 21:25:01", "start_date_local": "2015-10-11 05:25:01", "location_country": "\u6ca7\u6797\u4e1c\u4e09\u8def, \u6d77\u6ca7\u533a, \u53a6\u95e8\u5e02, \u6d77\u6ca7\u533a, \u53a6\u95e8\u5e02, \u798f\u5efa\u7701, 361022, \u4e2d\u56fd", "summary_polyline": "{{mtCg~moULf@hBh@jGaH|AqC`@]fAVhEdEd@]dh@lg@|HtFfGbDpGvB`GnAbJz@zIR~F[rPwCdPmHla@{VyNvJuVtNoFdC}H|BwK~A}LX}Jy@_L{BgNoGuIkG_h@{g@sK{Lmk@aj@kRiVcFeEsEgC`HdEbFrEpUdY~P`QvDlCv[`]u@j@gGeFqKfM", "average_heartrate": 147.0, "average_speed": 2.4963080422697637, "streak": 4}, {"run_id": 1444598841000, "name": "run from gpx", "distance": 14277.86366667498, "moving_time": "1:11:20", "type": "Run", "start_date": "2015-10-11 21:27:21", "start_date_local": "2015-10-12 05:27:21", "location_country": "\u6ca7\u6797\u4e1c\u4e09\u8def, \u6d77\u6ca7\u533a, \u53a6\u95e8\u5e02, \u6d77\u6ca7\u533a, \u53a6\u95e8\u5e02, \u798f\u5efa\u7701, 361022, \u4e2d\u56fd", "summary_polyline": "c|mtC}|moUlAnAt@Q~KuNtFhF~@g@dk@dk@lLzG|OtEdQpApQ_AjMwCjK_FeF~CiJ~CwKbB_O`@qLaAkHyAcJaDsIcF}D_DeZe[gBcAiMsMbh@ph@zIjHvNdHjO`DfTn@bJw@lJsBbJyD|f@oZmk@d]yLrDcTtBkFOwL}AoI{BaJwDwJ_Hkf@}e@mBWiFgFeKjL", "average_heartrate": 154.0, "average_speed": 3.335949454830603, "streak": 5}, {"run_id": 1445203521000, "name": "run from gpx", "distance": 5066.162649299884, "moving_time": "0:27:16", "type": "Run", "start_date": "2015-10-18 21:25:21", "start_date_local": "2015-10-19 05:25:21", "location_country": "\u6ca7\u6797\u4e1c\u4e09\u8def, \u6d77\u6ca7\u533a, \u53a6\u95e8\u5e02, \u6d77\u6ca7\u533a, \u53a6\u95e8\u5e02, \u798f\u5efa\u7701, 361022, \u4e2d\u56fd", "summary_polyline": "w{mtCe_noU|BhBdGyG|BwD`@HbFvErAQ\\X~g@ng@fJjGnFbC|K~CtLfAlJBbEWtDiAm@PFX`D]gJlA{IL}QqAaImBqOeI}HmGcSwS", "average_heartrate": 151.0, "average_speed": 3.096676436002374, "streak": 1}, {"run_id": 1445210425000, "name": "run from gpx", "distance": 1293.551327061244, "moving_time": "0:04:23", "type": "Run", "start_date": "2015-10-18 23:20:25", "start_date_local": "2015-10-19 07:20:25", "location_country": "\u6ee8\u6e56\u4e1c\u8def, \u6d77\u6ca7\u533a, \u53a6\u95e8\u5e02, \u6d77\u6ca7\u533a, \u53a6\u95e8\u5e02, \u798f\u5efa\u7701, 361022, \u4e2d\u56fd", "summary_polyline": "qkntCgyloUPIrAj]dAvGvAzA|EgC`FAJ`FjCjCBt@w@bB", "average_heartrate": 117.0, "average_speed": 4.918446110499026, "streak": 1}, {"run_id": 1446010647000, "name": "run from gpx", "distance": 2154.648234574238, "moving_time": "0:11:22", "type": "Run", "start_date": "2015-10-28 05:37:27", "start_date_local": "2015-10-28 13:37:27", "location_country": "\u6d77\u6ca7\u533a, \u53a6\u95e8\u5e02, \u6d77\u6ca7\u533a, \u53a6\u95e8\u5e02, \u798f\u5efa\u7701, \u4e2d\u56fd", "summary_polyline": "{uwtCknboUd@HfN}Df@ug@n@s@j_A|A", "average_heartrate": 136.0, "average_speed": 3.1593082618390587, "streak": 1}, {"run_id": 1446153753000, "name": "run from gpx", "distance": 10002.50978347573, "moving_time": "0:56:00", "type": "Run", "start_date": "2015-10-29 21:22:33", "start_date_local": "2015-10-30 05:22:33", "location_country": "\u6ca7\u6797\u4e1c\u4e09\u8def, \u6d77\u6ca7\u533a, \u53a6\u95e8\u5e02, \u6d77\u6ca7\u533a, \u53a6\u95e8\u5e02, \u798f\u5efa\u7701, 361022, \u4e2d\u56fd", "summary_polyline": "e{mtCc~moU\\r@`ARtFoGrBoDx@QrDfD~Cr@hf@rf@dLxHpPbGjTvBhKWnH}@rOkEtj@_]md@pY}LdFuP`DmRRaK{AmKuCkIoD_HcFyXsYkJmI_JwKsl@}j@g@v@jb@pb@m@v@", "average_heartrate": 156.0, "average_speed": 2.9769374355582534, "streak": 1}, {"run_id": 1447668875000, "name": "run from gpx", "distance": 5743.201191762772, "moving_time": "0:32:35", "type": "Run", "start_date": "2015-11-16 10:14:35", "start_date_local": "2015-11-16 18:14:35", "location_country": "\u6ca7\u6797\u4e1c\u4e09\u8def, \u6d77\u6ca7\u533a, \u53a6\u95e8\u5e02, \u6d77\u6ca7\u533a, \u53a6\u95e8\u5e02, \u798f\u5efa\u7701, 361022, \u4e2d\u56fd", "summary_polyline": "czmtCq{moU~ASlJ}MpFdGt@m@t@d@zRbTrElDfKhKvLlIxGjClJ`CnPvAvGOuKKmM}AgKeCuFgCaKcHmg@kg@WS{@t@wOuNsB~AaGbJeF}C", "average_heartrate": 151.0, "average_speed": 2.937698819315996, "streak": 1}, {"run_id": 1447756488000, "name": "run from gpx", "distance": 5669.824235647456, "moving_time": "0:31:10", "type": "Run", "start_date": "2015-11-17 10:34:48", "start_date_local": "2015-11-17 18:34:48", "location_country": "\u6ca7\u6797\u4e1c\u4e09\u8def, \u6d77\u6ca7\u533a, \u53a6\u95e8\u5e02, \u6d77\u6ca7\u533a, \u53a6\u95e8\u5e02, \u798f\u5efa\u7701, 361022, \u4e2d\u56fd", "summary_polyline": "{{mtC_~moUvAlA^OdKgN~FdGb@]l@FxArAbe@he@`LtHxK`E`I`BbOx@rESkGNeNqAwJwBcI{C_MqIig@qg@y@b@i@QyMaMa@OaAb@gDbGmCdCuAa@", "average_heartrate": 163.0, "average_speed": 3.0319915698649496, "streak": 2}, {"run_id": 1448143405000, "name": "run from gpx", "distance": 9768.659371085481, "moving_time": "0:55:56", "type": "Run", "start_date": "2015-11-21 22:03:25", "start_date_local": "2015-11-22 06:03:25", "location_country": "\u8297\u57ce\u533a, \u4e1c\u94fa\u5934\u8857\u9053, \u8297\u57ce\u533a, \u6f33\u5dde\u5e02, \u798f\u5efa\u7701, 363005, \u4e2d\u56fd", "summary_polyline": "ohrtCyh_mUzEBt@_Am@qAeEOm@z@Dh@|@l@rDHl@}@k@oAsDM{@`@Kh@h@`AtDP|@e@Di@c@}@_EQw@l@j@pBlEAj@_A{@{AgEAi@v@VjA`@RhE?b@gAm@aAiEMs@r@Bh@t@t@~DJ`@UPiAs@y@_EC{@nAr@|@bENx@kAg@cAeFGa@fANf@hAb@`DAn@{@Ec@y@q@gE@]fAt@z@jDN|@c@Fg@cAmAaECg@~At@v@rDHbA_Ai@uA{DOg@Fa@`A~@lApDJz@aACg@{@o@{DIm@rAj@|@zELf@gAm@gA{EKi@dA`AnAfE@`@aAc@eA_ES_Ad@If@f@bAtEPt@qAk@_AqEOs@hA`@`A|ERl@{@e@oA{DOeAn@?h@r@t@vDH|@m@@k@q@y@}CMyAr@`@xArETf@]?mA]]kDWwAt@`@rAfFPd@cAw@kAcEIo@z@v@xApDJ`AkAs@iAwDM{@n@LjAb@XpEDb@cAaAmAoDE}@n@Bp@l@l@vDL`Ay@m@wAsDGcAd@JlA^X|DLt@m@Bi@o@y@}DOs@r@r@|A|DFp@s@K{@e@[_EMs@p@RlAb@PtDHj@UJi@a@eAeEQ", "average_heartrate": 164.0, "average_speed": 2.910804341801395, "streak": 1}, {"run_id": 1448313364000, "name": "run from gpx", "distance": 10017.63869709825, "moving_time": "0:58:29", "type": "Run", "start_date": "2015-11-23 21:16:04", "start_date_local": "2015-11-24 05:16:04", "location_country": "\u6ca7\u6797\u4e1c\u4e09\u8def, \u6d77\u6ca7\u533a, \u53a6\u95e8\u5e02, \u6d77\u6ca7\u533a, \u53a6\u95e8\u5e02, \u798f\u5efa\u7701, 361022, \u4e2d\u56fd", "summary_polyline": "w{mtCy~moU~B`BdFyGfBqDbAA`GzE`Am@r^x_@xNvLlPhIlK~BrJv@rRc@hMiClJ{Dbg@uZug@tZyMbFqXdDqL_AqR}E{IaEoEeDa~A{}A]^Rf@`NjOrFjEpJrL", "average_heartrate": 156.0, "average_speed": 2.8548414639778423, "streak": 1}, {"run_id": 1449524503000, "name": "run from gpx", "distance": 3505.475626959414, "moving_time": "0:19:40", "type": "Run", "start_date": "2015-12-07 21:41:43", "start_date_local": "2015-12-08 05:41:43", "location_country": "\u6ca7\u6797\u4e1c\u4e09\u8def, \u6d77\u6ca7\u533a, \u53a6\u95e8\u5e02, \u6d77\u6ca7\u533a, \u53a6\u95e8\u5e02, \u798f\u5efa\u7701, 361022, \u4e2d\u56fd", "summary_polyline": "e|mtCa_noUbAnAbANhK_NhGpFdAUvg@zg@xFxD_FoCqh@oh@}A?_F{EiLrM", "average_heartrate": 160.0, "average_speed": 2.9707420567452663, "streak": 1}, {"run_id": 1456735274000, "name": "run from gpx", "distance": 4272.767236532663, "moving_time": "0:25:28", "type": "Run", "start_date": "2016-02-29 08:41:14", "start_date_local": "2016-02-29 16:41:14", "location_country": "\u5929\u5fc3\u5c9b\u5c0f\u5b66, \u6ee8\u6e56\u4e1c\u8def, \u6d77\u6ca7\u533a, \u53a6\u95e8\u5e02, \u6d77\u6ca7\u533a, \u53a6\u95e8\u5e02, \u798f\u5efa\u7701, 361022, \u4e2d\u56fd", "summary_polyline": "s}mtCscnoUnAdCjAVvD}B~DiF`AKxGtFFu@\\H`^p\\~JxKhFbD|LlFvHnBbNdAbG@}CNiI]gFm@aKeCqNgHmG}EcOaO", "average_heartrate": 163.0, "average_speed": 2.796313636474256, "streak": 1}, {"run_id": 1457959052000, "name": "run from gpx", "distance": 2884.902599359305, "moving_time": "0:16:15", "type": "Run", "start_date": "2016-03-14 12:37:32", "start_date_local": "2016-03-14 20:37:32", "location_country": "\u6d77\u6ca7\u533a, \u53a6\u95e8\u5e02, \u5d69\u5c7f\u8857\u9053, \u53a6\u95e8\u5e02, \u798f\u5efa\u7701, 361022, \u4e2d\u56fd", "summary_polyline": "{`mtCqdnoU`e@je@xHdG{I{Gac@oc@s@i@eAl@wFmFcLtMq@[", "average_heartrate": 153.0, "average_speed": 2.9588744608813387, "streak": 1}, {"run_id": 1458215100000, "name": "run from gpx", "distance": 5559.113602619325, "moving_time": "0:31:25", "type": "Run", "start_date": "2016-03-17 11:45:00", "start_date_local": "2016-03-17 19:45:00", "location_country": "\u6ca7\u6797\u4e1c\u4e09\u8def, \u6d77\u6ca7\u533a, \u53a6\u95e8\u5e02, \u6d77\u6ca7\u533a, \u53a6\u95e8\u5e02, \u798f\u5efa\u7701, 361022, \u4e2d\u56fd", "summary_polyline": "szmtCk~moU[h@fBrAhDmFjAo@zCiFdGhFx@UrFnEjb@fb@`J~F`NtFrKvBnJ^rE_@wHJeMeA{KkC}FaCcHiEwF}Emc@gc@cAc@s@RkFiF_Af@qBhDoBn@m@bCiAbBuBeBEk@", "average_heartrate": 172.0, "average_speed": 2.949131884678687, "streak": 1}, {"run_id": 1458737202000, "name": "run from gpx", "distance": 5589.060457781169, "moving_time": "0:32:19", "type": "Run", "start_date": "2016-03-23 12:46:42", "start_date_local": "2016-03-23 20:46:42", "location_country": "\u6ca7\u6797\u4e1c\u4e09\u8def, \u6d77\u6ca7\u533a, \u53a6\u95e8\u5e02, \u6d77\u6ca7\u533a, \u53a6\u95e8\u5e02, \u798f\u5efa\u7701, 361022, \u4e2d\u56fd", "summary_polyline": "czmtCq~moUN|@v@C~ByBvAyFzA_CnDjB~DpDr@k@ZLde@te@hNzJfHxC~LlCtIp@fJGcH^sOaBkFkAyM_FyJaHwf@yf@e@Uo@^_F}Ea@IaClEeGjGiCoBr@eA", "average_heartrate": 164.0, "average_speed": 2.882444795142429, "streak": 1}, {"run_id": 1459858165000, "name": "run from gpx", "distance": 5624.3388165807955, "moving_time": "0:30:27", "type": "Run", "start_date": "2016-04-05 12:09:25", "start_date_local": "2016-04-05 20:09:25", "location_country": "\u6ca7\u6797\u4e1c\u4e09\u8def, \u6d77\u6ca7\u533a, \u53a6\u95e8\u5e02, \u6d77\u6ca7\u533a, \u53a6\u95e8\u5e02, \u798f\u5efa\u7701, 361022, \u4e2d\u56fd", "summary_polyline": "yxmtCobnoU]TSU_@xAx@nAz@T~CcCh@{AbAq@@iAp@u@?o@\\[p@LbGhFr@_@~i@hi@zGjE|KbFnK`C|Ff@dML_CnB_B@eEqAgQaDiKsDiNeJmd@id@kB{AkAFwEsEgAh@gAhCsG|GoA}@", "average_heartrate": 158.0, "average_speed": 3.0784558383036646, "streak": 1}, {"run_id": 1461487331000, "name": "run from gpx", "distance": 5452.283265691663, "moving_time": "0:31:43", "type": "Run", "start_date": "2016-04-24 08:42:11", "start_date_local": "2016-04-24 16:42:11", "location_country": "\u6ca7\u6797\u4e1c\u4e09\u8def, \u6d77\u6ca7\u533a, \u53a6\u95e8\u5e02, \u6d77\u6ca7\u533a, \u53a6\u95e8\u5e02, \u798f\u5efa\u7701, 361022, \u4e2d\u56fd", "summary_polyline": "i{mtCibnoUYfBrCzAlEeI|BsCj@F~GjFh@]b@Txg@ng@bLpHzIbDpL~BrIf@bHAyEl@eL_AqKwBwI}C{NyJ{e@ye@_Ak@c@b@a@K}EyEkK~L", "average_heartrate": 164.0, "average_speed": 2.8650989309992974, "streak": 1}, {"run_id": 1471990162000, "name": "run from gpx", "distance": 1874.4336961089239, "moving_time": "0:11:17", "type": "Run", "start_date": "2016-08-23 22:09:22", "start_date_local": "2016-08-24 06:09:22", "location_country": "\u6d77\u6ca7\u533a, \u53a6\u95e8\u5e02, \u5d69\u5c7f\u8857\u9053, \u53a6\u95e8\u5e02, \u798f\u5efa\u7701, 361026, \u4e2d\u56fd", "summary_polyline": "umgtC{vkoUs@~AgAr@qLpAkA_VrBy@`GWfGoA~E?pAvTuIfBSmBnAO", "average_heartrate": 153.0, "average_speed": 2.768735149348484, "streak": 1}, {"run_id": 1472077240000, "name": "run from gpx", "distance": 1875.9212461752766, "moving_time": "0:11:03", "type": "Run", "start_date": "2016-08-24 22:20:40", "start_date_local": "2016-08-25 06:20:40", "location_country": "\u6d77\u6ca7\u533a, \u53a6\u95e8\u5e02, \u5d69\u5c7f\u8857\u9053, \u53a6\u95e8\u5e02, \u798f\u5efa\u7701, 361026, \u4e2d\u56fd", "summary_polyline": "emgtCovkoUm@DGpBqNhB[[aAqNRmFdJw@|EeAbFJZ\\hAdI`@hI{@h@wHp@UmBd@A", "average_heartrate": 163.0, "average_speed": 2.82944381021912, "streak": 2}, {"run_id": 1488585865000, "name": "run from gpx", "distance": 2570.86206991386, "moving_time": "0:15:09", "type": "Run", "start_date": "2017-03-04 00:04:25", "start_date_local": "2017-03-04 08:04:25", "location_country": "\u6d77\u6ca7\u533a, \u53a6\u95e8\u5e02, \u5d69\u5c7f\u8857\u9053, \u53a6\u95e8\u5e02, \u798f\u5efa\u7701, 361026, \u4e2d\u56fd", "summary_polyline": "iogtCyukoUM~Ae@PwLjAiBwPHsDrLaBtLHJnAn@l@PnOsH~AiOzAs@[qAwU~Ae@fDA", "average_heartrate": 166.0, "average_speed": 2.828231100015248, "streak": 1}, {"run_id": 1489566300000, "name": "run from gpx", "distance": 5120.357029759773, "moving_time": "0:30:36", "type": "Run", "start_date": "2017-03-15 08:25:00", "start_date_local": "2017-03-15 16:25:00", "location_country": "\u6d77\u6ca7\u533a, \u53a6\u95e8\u5e02, \u5d69\u5c7f\u8857\u9053, \u53a6\u95e8\u5e02, \u798f\u5efa\u7701, 361026, \u4e2d\u56fd", "summary_polyline": "ongtC{ukoUk@m@]yBuCu@y@yGk@aAgAe@oBRkB{@s@wSc@iAcYnP}HjCgI|A}Hz@wI?eG[sMyB~CfAhMpArV{@tIcB|IsCxU}MrAhAr@xQ|@jBAbJh@xIh@P", "average_heartrate": 169.0, "average_speed": 2.7888654846186127, "streak": 1}, {"run_id": 1490000046000, "name": "run from gpx", "distance": 5103.459881281759, "moving_time": "0:30:28", "type": "Run", "start_date": "2017-03-20 08:54:06", "start_date_local": "2017-03-20 16:54:06", "location_country": "\u6d77\u6ca7\u533a, \u53a6\u95e8\u5e02, \u5d69\u5c7f\u8857\u9053, \u53a6\u95e8\u5e02, \u798f\u5efa\u7701, 361026, \u4e2d\u56fd", "summary_polyline": "algtC}wkoUo@Eg@o@_@iD}BCaA{BDgCq@aA}Aa@{Cb@[YiBwSy@wAeA`AmB^oCjCiMnHoPhFaJdAeLN}MoAuFoArK|BhH`@pI?jIq@rRyEpW}NvAtBv@jOv@dBInDp@`H@hG", "average_heartrate": 175.0, "average_speed": 2.791827068534879, "streak": 1}, {"run_id": 1490602257000, "name": "run from gpx", "distance": 5024.42321607489, "moving_time": "0:29:42", "type": "Run", "start_date": "2017-03-27 08:10:57", "start_date_local": "2017-03-27 16:10:57", "location_country": "\u6d77\u6ca7\u533a, \u53a6\u95e8\u5e02, \u5d69\u5c7f\u8857\u9053, \u53a6\u95e8\u5e02, \u798f\u5efa\u7701, 361026, \u4e2d\u56fd", "summary_polyline": "wlgtCivkoUaAq@aAeCwCm@iAmCb@sBSy@_@U_ETqAu@s@sB_@cQ[cAuUdNqKbE_HvAcK~@uHJsHe@uLwBbEhAvMfA~IAzJq@fGgAfJ}CzXwO`@Tj@rEh@nN|@h@rFEZrD", "average_heartrate": 167.0, "average_speed": 2.8195416476290065, "streak": 1}, {"run_id": 1490692024000, "name": "run from gpx", "distance": 3289.6137009993513, "moving_time": "0:19:53", "type": "Run", "start_date": "2017-03-28 09:07:04", "start_date_local": "2017-03-28 17:07:04", "location_country": "\u6d77\u6ca7\u4f53\u80b2\u4e2d\u5fc3\u4f53\u80b2\u573a, \u6e56\u5cb8\u5357\u8def, \u6d77\u6ca7\u533a, \u53a6\u95e8\u5e02, \u6d77\u6ca7\u533a, \u53a6\u95e8\u5e02, \u798f\u5efa\u7701, 361026, \u4e2d\u56fd", "summary_polyline": "gektCizjoUa@BPg@eEiBe@v@h@zGnCWzB}AxDs@nB_COaCcAqBeAk@gCWwCjDAhCd@j@`CbAvBJzBqA\\yBm@sBwAqAcDUuAt@q@nA?`DbAlAnCt@vBa@|AiBFoAe@gBw@}@wCi@kALwAhAYzEbEjBpBGtBcBUkE{AqA{DY_BrAa@vB", "average_heartrate": 147.0, "average_speed": 2.7574297577530187, "streak": 2}, {"run_id": 1500981689000, "name": "run from gpx", "distance": 2985.0584769630323, "moving_time": "0:18:01", "type": "Run", "start_date": "2017-07-25 11:21:29", "start_date_local": "2017-07-25 19:21:29", "location_country": "\u6d77\u6ca7\u533a, \u53a6\u95e8\u5e02, \u5d69\u5c7f\u8857\u9053, \u53a6\u95e8\u5e02, \u798f\u5efa\u7701, 361026, \u4e2d\u56fd", "summary_polyline": "slgtCkvkoUw@[gA{BoBOoAwIk@m@sGPs@uEg@}MwAgA}WhOuOfEaPhBkM_AeKeBzTxB", "average_heartrate": 171.0, "average_speed": 2.7613861951554415, "streak": 1}, {"run_id": 1505388145000, "name": "run from gpx", "distance": 3659.4090547754977, "moving_time": "0:22:44", "type": "Run", "start_date": "2017-09-14 11:22:25", "start_date_local": "2017-09-14 19:22:25", "location_country": "\u6d77\u6ca7\u533a, \u53a6\u95e8\u5e02, \u5d69\u5c7f\u8857\u9053, \u53a6\u95e8\u5e02, \u798f\u5efa\u7701, 361026, \u4e2d\u56fd", "summary_polyline": "iogtC_vkoUQBPjAo@b@gNvAoYhHoYvFaAW?oIs@qGg@uO`@u@C_AlMkB|HiC`YwOhAlAnApQr@r@bGUj@t@", "average_heartrate": 155.0, "average_speed": 2.6828512131785174, "streak": 1}, {"run_id": 1505471074000, "name": "run from gpx", "distance": 3708.714299717832, "moving_time": "0:22:49", "type": "Run", "start_date": "2017-09-15 10:24:34", "start_date_local": "2017-09-15 18:24:34", "location_country": "\u6d77\u6ca7\u533a, \u53a6\u95e8\u5e02, \u5d69\u5c7f\u8857\u9053, \u53a6\u95e8\u5e02, \u798f\u5efa\u7701, 361026, \u4e2d\u56fd", "summary_polyline": "}ogtCgvkoU@zAs@f@aMlA{OvDaE`@oBdAcZ~Fw@KgBcSLqEo@uHb@sBzIu@nLuDrYwOjAt@ThAd@nMd@dCVTdGe@`@J`@lB", "average_heartrate": 172.0, "average_speed": 2.709068151729607, "streak": 2}, {"run_id": 1505555517000, "name": "run from gpx", "distance": 3032.7132885547917, "moving_time": "0:17:44", "type": "Run", "start_date": "2017-09-16 09:51:57", "start_date_local": "2017-09-16 17:51:57", "location_country": "X435, \u6d77\u6ca7\u533a, \u53a6\u95e8\u5e02, \u6d77\u6ca7\u533a, \u53a6\u95e8\u5e02, \u798f\u5efa\u7701, 361026, \u4e2d\u56fd", "summary_polyline": "{|gtCepkoUmAFMg@sB}k@i@qA_TxMmFzBsFnBwOvCOpDh@jMv@lAL`FSdDTxBpYkF", "average_heartrate": 179.0, "average_speed": 2.8502944441304434, "streak": 3}, {"run_id": 1505648540000, "name": "run from gpx", "distance": 3754.4992088904946, "moving_time": "0:22:30", "type": "Run", "start_date": "2017-09-17 11:42:20", "start_date_local": "2017-09-17 19:42:20", "location_country": "\u6d77\u6ca7\u533a, \u53a6\u95e8\u5e02, \u5d69\u5c7f\u8857\u9053, \u53a6\u95e8\u5e02, \u798f\u5efa\u7701, 361026, \u4e2d\u56fd", "summary_polyline": "ungtCevkoUFtAo@h@gMrA_@Ss@aHqAkb@cAKeO`JwMfGaTzD`@zS|@xMl@l@zPoEn`@yH", "average_heartrate": 165.0, "average_speed": 2.78111052510407, "streak": 4}, {"run_id": 1508318843000, "name": "run from gpx", "distance": 4102.8268119673885, "moving_time": "0:27:28", "type": "Run", "start_date": "2017-10-18 09:27:23", "start_date_local": "2017-10-18 17:27:23", "location_country": "\u6d77\u6ca7\u533a, \u53a6\u95e8\u5e02, \u5d69\u5c7f\u8857\u9053, \u53a6\u95e8\u5e02, \u798f\u5efa\u7701, 361026, \u4e2d\u56fd", "summary_polyline": "wngtCwukoUDd@kAhAiMtA}PhEgd@|Ie@{DJ{B_ByZdNuBpH_C|[wPz@|Ox@`Ez@bU|AGjMgF", "average_heartrate": 158.0, "average_speed": 2.4895793761938037, "streak": 1}, {"run_id": 1509354569000, "name": "run from gpx", "distance": 3790.5391208257133, "moving_time": "0:22:39", "type": "Run", "start_date": "2017-10-30 09:09:29", "start_date_local": "2017-10-30 17:09:29", "location_country": "\u6d77\u6ca7\u533a, \u53a6\u95e8\u5e02, \u5d69\u5c7f\u8857\u9053, \u53a6\u95e8\u5e02, \u798f\u5efa\u7701, 361026, \u4e2d\u56fd", "summary_polyline": "ulgtC_wkoUw@XGbBi@`@yMzAsl@lM{H~@s@cHiAaZz@o@pK_BnKaDlXuOf@@TvA|@zVr@nEXtI", "average_heartrate": 147.0, "average_speed": 2.789212009437611, "streak": 1}, {"run_id": 1517818287000, "name": "run from gpx", "distance": 3849.506101652799, "moving_time": "0:19:59", "type": "Run", "start_date": "2018-02-05 08:11:27", "start_date_local": "2018-02-05 16:11:27", "location_country": "\u6d77\u6ca7\u533a, \u53a6\u95e8\u5e02, \u5d69\u5c7f\u8857\u9053, \u53a6\u95e8\u5e02, \u798f\u5efa\u7701, 361026, \u4e2d\u56fd", "summary_polyline": "_mgtC{tkoUm@OU`Bs@b@sNdAik@bMmGdAaAS}@oD}@cAj@gC}@{AhAcC~CiD}@p@AuAqAe@[y@O_Fl@q@`N}BfIeCnYyOdB|SZThDo@", "average_heartrate": 154.0, "average_speed": 3.2105972490849033, "streak": 1}, {"run_id": 1535607515000, "name": "run from gpx", "distance": 2824.716331516208, "moving_time": "1:07:33", "type": "Run", "start_date": "2018-08-30 05:38:35", "start_date_local": "2018-08-30 13:38:35", "location_country": "X436, \u6d77\u6ca7\u533a, \u53a6\u95e8\u5e02, \u5d69\u5c7f\u8857\u9053, \u53a6\u95e8\u5e02, \u798f\u5efa\u7701, 361026, \u4e2d\u56fd", "summary_polyline": "wdgtC{ukoU@p@f@o@_@|@n@VqBIV][a@d@Ze@QI`Ay@{@A^Ac@Hb@u@c@rARoA_Af@pA\\OC~@_@cAv@d@?XYWkBeDhAnB\\ITxAUq@k@h@x@Ba@gAb@\\g@IAh@b@_@_@EDg@Cp@j@Eu@CLg@XHa@\\ZSa@FZQOQh@Vm@DYg@~@`ACTSg@a@LVIOo@Nd@c@Ll@KF`@k@a@^l@_CyAbC`A{As@t@^Db@wAeAbBd@GPnACeCy@b@bAR_AEt@h@Ek@BK]b@d@RU_@DXTo@i@x@~@Mi@YB`@POw@Q\\V\\WUNWWF`@L@UWt@Lk@FTe@c@SpAn@m@[G^\\He@YJKgATx@Qt@^oBA|@UDN]Rh@c@LLk@", "average_heartrate": 154.0, "average_speed": 0.6969445673615119, "streak": 1}, {"run_id": 1554018359000, "name": "run from gpx", "distance": 3038.6749045148454, "moving_time": "0:17:37", "type": "Run", "start_date": "2019-03-31 07:45:59", "start_date_local": "2019-03-31 15:45:59", "location_country": "\u6d77\u6ca7\u533a, \u53a6\u95e8\u5e02, \u5d69\u5c7f\u8857\u9053, \u53a6\u95e8\u5e02, \u798f\u5efa\u7701, 361026, \u4e2d\u56fd", "summary_polyline": "_lgtCqwkoUoAXe@dBiD`A{I`Au_@|I_UnDcAkK]sSb@mCtLgBjJ}C~X{O", "average_heartrate": 164.0, "average_speed": 2.8748106949052463, "streak": 1}, {"run_id": 1554107219000, "name": "run from gpx", "distance": 3746.2778303759846, "moving_time": "0:23:00", "type": "Run", "start_date": "2019-04-01 08:26:59", "start_date_local": "2019-04-01 16:26:59", "location_country": "\u6d77\u6ca7\u533a, \u53a6\u95e8\u5e02, \u5d69\u5c7f\u8857\u9053, \u53a6\u95e8\u5e02, \u798f\u5efa\u7701, 361026, \u4e2d\u56fd", "summary_polyline": "_mgtCuvkoUw@DO~AcBx@eFPeH`BoBFim@|MgAEyBib@?u@b@S`MwAbKqDlRyK|EsB|ArS`@RlA]bEJn@bAb@fD", "average_heartrate": 173.0, "average_speed": 2.7146940799825976, "streak": 2}, {"run_id": 1554290857000, "name": "run from gpx", "distance": 4062.952365607049, "moving_time": "0:22:49", "type": "Run", "start_date": "2019-04-03 11:27:37", "start_date_local": "2019-04-03 19:27:37", "location_country": "\u6d77\u6ca7\u533a, \u53a6\u95e8\u5e02, \u5d69\u5c7f\u8857\u9053, \u53a6\u95e8\u5e02, \u798f\u5efa\u7701, 361026, \u4e2d\u56fd", "summary_polyline": "wkgtCgwkoUcBZXfA]XaCn@kQfBkSvF{[fGgA_NjEuDcEP}@qECkI|MoBjKgDnIwDfN{Ij@LjAvRt@^lGg@v@tBz@xFlAf@", "average_heartrate": 167.0, "average_speed": 2.967824956615814, "streak": 1}, {"run_id": 1554369105000, "name": "run from gpx", "distance": 3860.6553486061657, "moving_time": "0:22:51", "type": "Run", "start_date": "2019-04-04 09:11:45", "start_date_local": "2019-04-04 17:11:45", "location_country": "X435, \u6d77\u6ca7\u533a, \u53a6\u95e8\u5e02, \u6d77\u6ca7\u533a, \u53a6\u95e8\u5e02, \u798f\u5efa\u7701, 361026, \u4e2d\u56fd", "summary_polyline": "ukgtCevkoUqAvBkPxAup@|NsC^[YsBia@Lo@~MgClJqCtXyOb@IRb@dAfRxI@t@hEGbCPd@rBR", "average_heartrate": 172.0, "average_speed": 2.815941173308655, "streak": 2}, {"run_id": 1554548760000, "name": "run from gpx", "distance": 4285.276532077507, "moving_time": "0:24:55", "type": "Run", "start_date": "2019-04-06 11:06:00", "start_date_local": "2019-04-06 19:06:00", "location_country": "\u6d77\u6ca7\u533a, \u53a6\u95e8\u5e02, \u5d69\u5c7f\u8857\u9053, \u53a6\u95e8\u5e02, \u798f\u5efa\u7701, 361026, \u4e2d\u56fd", "summary_polyline": "klgtCuwkoU_AZAfBcAv@gMjAWo@u@gTLwAg@_DWgKYwAu@EcVxNmLtD{MnBm@h@bAfMzAJ\\l@jDExC`@a@vBoDbCKn@}Bv@eAhETp@bAKxQsE~a@kI", "average_heartrate": 157.0, "average_speed": 2.8664057070752555, "streak": 1}, {"run_id": 1554636725000, "name": "run from gpx", "distance": 4158.8828096422685, "moving_time": "0:26:22", "type": "Run", "start_date": "2019-04-07 11:32:05", "start_date_local": "2019-04-07 19:32:05", "location_country": "\u6d77\u6ca7\u533a, \u53a6\u95e8\u5e02, \u5d69\u5c7f\u8857\u9053, \u53a6\u95e8\u5e02, \u798f\u5efa\u7701, 361026, \u4e2d\u56fd", "summary_polyline": "clgtCuwkoU{@RE~AwAx@_LnAy@e@i@aIJuL}AcVWa@yZdQ{FpByOpCc@|AFbFnCxXKjCvt@qPzLsA", "average_heartrate": 165.0, "average_speed": 2.628876617978678, "streak": 2}, {"run_id": 1554807686000, "name": "run from gpx", "distance": 1800.7125452703992, "moving_time": "0:14:04", "type": "Run", "start_date": "2019-04-09 11:01:26", "start_date_local": "2019-04-09 19:01:26", "location_country": "\u6d77\u6ca7\u533a, \u53a6\u95e8\u5e02, \u5d69\u5c7f\u8857\u9053, \u53a6\u95e8\u5e02, \u798f\u5efa\u7701, 361026, \u4e2d\u56fd", "summary_polyline": "skgtCgwkoUmBT[kDnCyGFaB]y@mFBeLbAi@}@QqMFrEv@nFp@`@lFIl@bA|@rHbCdAr@|B", "average_heartrate": 130.0, "average_speed": 2.133545669751658, "streak": 1}, {"run_id": 1555327856000, "name": "run from gpx", "distance": 4135.37120451728, "moving_time": "0:22:37", "type": "Run", "start_date": "2019-04-15 11:30:56", "start_date_local": "2019-04-15 19:30:56", "location_country": "X436, \u6d77\u6ca7\u533a, \u53a6\u95e8\u5e02, \u5d69\u5c7f\u8857\u9053, \u53a6\u95e8\u5e02, \u798f\u5efa\u7701, 361026, \u4e2d\u56fd", "summary_polyline": "yhgtCaykoUoC`A{@hCsKvAoB?}Bai@UwAo@M}KdHaNxGaJpCoLdB|B`c@hIiAzj@eMtNwA", "average_heartrate": 154.0, "average_speed": 3.0474364071608546, "streak": 1}, {"run_id": 1555499780000, "name": "run from gpx", "distance": 4215.212609865017, "moving_time": "0:23:55", "type": "Run", "start_date": "2019-04-17 11:16:20", "start_date_local": "2019-04-17 19:16:20", "location_country": "X435, \u6d77\u6ca7\u533a, \u53a6\u95e8\u5e02, \u6d77\u6ca7\u533a, \u53a6\u95e8\u5e02, \u798f\u5efa\u7701, 361026, \u4e2d\u56fd", "summary_polyline": "ijgtCgxkoUiBb@]|BaMhBcASg@eFQgMuAuMLiIa@o@aZrPsIpCwMlCMhE|@zMTrIQdBhA|CfMcEfIoArO{DzJuBxNaB", "average_heartrate": 156.0, "average_speed": 2.9374303901498378, "streak": 1}, {"run_id": 1557832754000, "name": "run from gpx", "distance": 3861.065301164337, "moving_time": "0:22:06", "type": "Run", "start_date": "2019-05-14 11:19:14", "start_date_local": "2019-05-14 19:19:14", "location_country": "\u6d77\u6ca7\u533a, \u53a6\u95e8\u5e02, \u5d69\u5c7f\u8857\u9053, \u53a6\u95e8\u5e02, \u798f\u5efa\u7701, 361026, \u4e2d\u56fd", "summary_polyline": "}lgtCwwkoU{@\\DzAq@p@sMnByAcWc@{SIk@iALiS~KgIlDcGhBwLtB|@bPjClFeBjCFxE\\Zvq@yN", "average_heartrate": 157.0, "average_speed": 2.911813952612622, "streak": 1}, {"run_id": 1559215618000, "name": "run from gpx", "distance": 4108.67758313651, "moving_time": "0:24:35", "type": "Run", "start_date": "2019-05-30 11:26:58", "start_date_local": "2019-05-30 19:26:58", "location_country": "\u6d77\u6ca7\u533a, \u53a6\u95e8\u5e02, \u5d69\u5c7f\u8857\u9053, \u53a6\u95e8\u5e02, \u798f\u5efa\u7701, 361026, \u4e2d\u56fd", "summary_polyline": "olgtCsvkoU}Bz@EtAsMxA}@sODoFyAsToAPeXnOaIpC}OzBh@tDJxLn@vKh@dCr`@sHdTgFfNaB", "average_heartrate": 157.0, "average_speed": 2.785544124160346, "streak": 1}, {"run_id": 1560770831000, "name": "run from gpx", "distance": 3443.241701301742, "moving_time": "0:19:22", "type": "Run", "start_date": "2019-06-17 11:27:11", "start_date_local": "2019-06-17 19:27:11", "location_country": "\u6d77\u6ca7\u533a, \u53a6\u95e8\u5e02, \u5d69\u5c7f\u8857\u9053, \u53a6\u95e8\u5e02, \u798f\u5efa\u7701, 361026, \u4e2d\u56fd", "summary_polyline": "u_htC}|koUP}DOqBg@y@k@{Og@{Do@Kk\\jPsHxBeL|AHjAa@jAPdGUh@v@fA|A\\A|A~Bz@PzB_CnCs@dCEzBXl@bVaFvFg@xSiF", "average_heartrate": 153.0, "average_speed": 2.9632028410514133, "streak": 1}, {"run_id": 1565649752000, "name": "run from gpx", "distance": 2801.549479811477, "moving_time": "0:17:03", "type": "Run", "start_date": "2019-08-12 22:42:32", "start_date_local": "2019-08-13 06:42:32", "location_country": "X435, \u6d77\u6ca7\u533a, \u53a6\u95e8\u5e02, \u6d77\u6ca7\u533a, \u53a6\u95e8\u5e02, \u798f\u5efa\u7701, 361026, \u4e2d\u56fd", "summary_polyline": "elgtCoukoU{@v@K`Ae@LsNl@oAyRa@mWC]w@IqZtPgKzC{KvA`@~Z`@hGb@T", "average_heartrate": 145.0, "average_speed": 2.7385625413601926, "streak": 1}, {"run_id": 1566468114000, "name": "run from gpx", "distance": 3079.9382758691304, "moving_time": "0:18:35", "type": "Run", "start_date": "2019-08-22 10:01:54", "start_date_local": "2019-08-22 18:01:54", "location_country": "X435, \u6d77\u6ca7\u533a, \u53a6\u95e8\u5e02, \u6d77\u6ca7\u533a, \u53a6\u95e8\u5e02, \u798f\u5efa\u7701, 361026, \u4e2d\u56fd", "summary_polyline": "grgtC}pkoU}Jl@s@i@FgDoAeLTqC]cA]qS[iAsEhAmChCaLzGv@I~RsLbAfADnFh@|Ah@~Gl@NFfCyAvFXdBbAdBL|Cz@f@xK{@", "average_heartrate": 172.0, "average_speed": 2.762276480600117, "streak": 1}, {"run_id": 1566551304000, "name": "run from gpx", "distance": 2994.256577920194, "moving_time": "0:19:14", "type": "Run", "start_date": "2019-08-23 09:08:24", "start_date_local": "2019-08-23 17:08:24", "location_country": "\u6d77\u6ca7\u533a, \u53a6\u95e8\u5e02, \u5d69\u5c7f\u8857\u9053, \u53a6\u95e8\u5e02, \u798f\u5efa\u7701, 361026, \u4e2d\u56fd", "summary_polyline": "cpgtCmukoU{@O_AmCuDE@_Ha@aBqCBkBq@XqE}@oEHeCg@_Cq\\dQr\\}Pv@dOd@pB~ID\\fGf@xAO^vBPp@`C", "average_heartrate": 161.0, "average_speed": 2.5946764106760782, "streak": 2}, {"run_id": 1566859623000, "name": "run from gpx", "distance": 3335.3749141815892, "moving_time": "0:19:18", "type": "Run", "start_date": "2019-08-26 22:47:03", "start_date_local": "2019-08-27 06:47:03", "location_country": "\u6d77\u6ca7\u533a, \u53a6\u95e8\u5e02, \u5d69\u5c7f\u8857\u9053, \u53a6\u95e8\u5e02, \u798f\u5efa\u7701, 361026, \u4e2d\u56fd", "summary_polyline": "ingtC}vkoU]`C]V}MfA_@yOiBc[s@oAe@?{TbNaJhDBh@vC_@|DcBfVoN`@h@dAtQp@l@nHa@r@nJX^|@?", "average_heartrate": 160.0, "average_speed": 2.880289217773393, "streak": 1}, {"run_id": 1566949409000, "name": "run from gpx", "distance": 2911.1141645518255, "moving_time": "0:17:35", "type": "Run", "start_date": "2019-08-27 23:43:29", "start_date_local": "2019-08-28 07:43:29", "location_country": "\u6d77\u6ca7\u533a, \u53a6\u95e8\u5e02, \u5d69\u5c7f\u8857\u9053, \u53a6\u95e8\u5e02, \u798f\u5efa\u7701, 361026, \u4e2d\u56fd", "summary_polyline": "slgtCkwkoUk@J_AtCcN|@{Cam@kAUwQrKtQuK`AhAt@`Pd@jCvCm@hD@dArDB|DhBb@bBhD", "average_heartrate": 163.0, "average_speed": 2.75934991900647, "streak": 2}, {"run_id": 1567033796000, "name": "run from gpx", "distance": 3110.757537725313, "moving_time": "0:19:03", "type": "Run", "start_date": "2019-08-28 23:09:56", "start_date_local": "2019-08-29 07:09:56", "location_country": "\u6d77\u6ca7\u533a, \u53a6\u95e8\u5e02, \u5d69\u5c7f\u8857\u9053, \u53a6\u95e8\u5e02, \u798f\u5efa\u7701, 361026, \u4e2d\u56fd", "summary_polyline": "ulgtC{vkoUi@?k@~BiM|Ac@MeAuQLuCcAuJEiHaAqAe@AcRhLyLxEXv@vFeB`XmOd@@lA`SzA\\zEUh@^", "average_heartrate": 153.0, "average_speed": 2.721572648928533, "streak": 3}, {"run_id": 1567119558000, "name": "run from gpx", "distance": 3290.335574412037, "moving_time": "0:19:31", "type": "Run", "start_date": "2019-08-29 22:59:18", "start_date_local": "2019-08-30 06:59:18", "location_country": "\u6d77\u6ca7\u533a, \u53a6\u95e8\u5e02, \u5d69\u5c7f\u8857\u9053, \u53a6\u95e8\u5e02, \u798f\u5efa\u7701, 361026, \u4e2d\u56fd", "summary_polyline": "klgtCyvkoUs@Jo@dCiLhA}@[mAiKOsYc@}Dm@w@gAPkU~MeIrCDZr@FpHaCtUaNZPNrAt@dPp@^rH]l@dJ", "average_heartrate": 155.0, "average_speed": 2.809851045612329, "streak": 4}, {"run_id": 1567290975000, "name": "run from gpx", "distance": 3298.3417955201817, "moving_time": "0:19:28", "type": "Run", "start_date": "2019-08-31 22:36:15", "start_date_local": "2019-09-01 06:36:15", "location_country": "\u6d77\u6ca7\u533a, \u53a6\u95e8\u5e02, \u5d69\u5c7f\u8857\u9053, \u53a6\u95e8\u5e02, \u798f\u5efa\u7701, 361026, \u4e2d\u56fd", "summary_polyline": "mlgtCyvkoUy@L[pBa@VyKjAaASiA_ONuAq@oTOuCe@gAkALyMnIqFrC_InC?X\\RtJcDvT_MtArSpIKv@~J", "average_heartrate": 148.0, "average_speed": 2.8239227701371417, "streak": 1}, {"run_id": 1567377809000, "name": "run from gpx", "distance": 3269.948022633906, "moving_time": "0:18:56", "type": "Run", "start_date": "2019-09-01 22:43:29", "start_date_local": "2019-09-02 06:43:29", "location_country": "\u6d77\u6ca7\u533a, \u53a6\u95e8\u5e02, \u5d69\u5c7f\u8857\u9053, \u53a6\u95e8\u5e02, \u798f\u5efa\u7701, 361026, \u4e2d\u56fd", "summary_polyline": "qmgtC_vkoUy@VSzA{KfA{@SsAaO_As[g@aAeV`NgJjDF^`GgAfY{OtAdUzCw@jEL`@nI", "average_heartrate": 133.0, "average_speed": 2.878475372036889, "streak": 2}, {"run_id": 1567464990000, "name": "run from gpx", "distance": 3254.4310997236885, "moving_time": "0:19:07", "type": "Run", "start_date": "2019-09-02 22:56:30", "start_date_local": "2019-09-03 06:56:30", "location_country": "\u6d77\u6ca7\u533a, \u53a6\u95e8\u5e02, \u5d69\u5c7f\u8857\u9053, \u53a6\u95e8\u5e02, \u798f\u5efa\u7701, 361026, \u4e2d\u56fd", "summary_polyline": "slgtCsvkoUa@Cg@hCWH}M`AyA_O_Ag\\o@{@eALaTjM_JdDPd@jDm@zEqBvTiMrAzRfAZhGIx@jCJxD", "average_heartrate": 153.0, "average_speed": 2.8373418480590136, "streak": 3}, {"run_id": 1567634728000, "name": "run from gpx", "distance": 3328.071155720663, "moving_time": "0:19:42", "type": "Run", "start_date": "2019-09-04 22:05:28", "start_date_local": "2019-09-05 06:05:28", "location_country": "\u6d77\u6ca7\u533a, \u53a6\u95e8\u5e02, \u5d69\u5c7f\u8857\u9053, \u53a6\u95e8\u5e02, \u798f\u5efa\u7701, 361026, \u4e2d\u56fd", "summary_polyline": "mlgtCewkoUoAVOtB]XyLzAi@c@A_EkAsJPmD{@{CVuDa@mKmA]}RjLyL`FP`@pG{AbYmOzAdS~@ZlFId@X|@pI", "average_heartrate": 141.0, "average_speed": 2.815627035296669, "streak": 1}, {"run_id": 1567893893000, "name": "run from gpx", "distance": 3227.589258309005, "moving_time": "0:19:20", "type": "Run", "start_date": "2019-09-07 22:04:53", "start_date_local": "2019-09-08 06:04:53", "location_country": "\u6d77\u6ca7\u533a, \u53a6\u95e8\u5e02, \u5d69\u5c7f\u8857\u9053, \u53a6\u95e8\u5e02, \u798f\u5efa\u7701, 361026, \u4e2d\u56fd", "summary_polyline": "kmgtCgvkoUu@JInBm@^yLh@e@_Qw@wFw@aRo@KqSxLmLpEhI{CpViN\\Zx@jR~@XvB[lDLf@vI", "average_heartrate": 149.0, "average_speed": 2.7824045330250042, "streak": 1}, {"run_id": 1568759199000, "name": "run from gpx", "distance": 3111.3572875569857, "moving_time": "0:18:39", "type": "Run", "start_date": "2019-09-17 22:26:39", "start_date_local": "2019-09-18 06:26:39", "location_country": "X435, \u6d77\u6ca7\u533a, \u53a6\u95e8\u5e02, \u6d77\u6ca7\u533a, \u53a6\u95e8\u5e02, \u798f\u5efa\u7701, 361026, \u4e2d\u56fd", "summary_polyline": "krgtCcrkoUdAcAOXb@f@Kf@gMp@e@o@gA}Qw@iYo@}@_SzLmMvFj@TnFaBrXkO|AvRx@X|GD", "average_heartrate": 154.0, "average_speed": 2.780480149738146, "streak": 1}, {"run_id": 1572254352000, "name": "run from gpx", "distance": 3355.236308259531, "moving_time": "0:20:27", "type": "Run", "start_date": "2019-10-28 09:19:12", "start_date_local": "2019-10-28 17:19:12", "location_country": "\u6d77\u6ca7\u533a, \u53a6\u95e8\u5e02, \u5d69\u5c7f\u8857\u9053, \u53a6\u95e8\u5e02, \u798f\u5efa\u7701, 361026, \u4e2d\u56fd", "summary_polyline": "gmgtCcwkoUo@`AHs@?lAwD|AsHz@m@MwBub@WwIPSa@m@wSlMqMnFDTfHiBpXeOt@xFZzJxA\\jG?p@fI", "average_heartrate": 154.0, "average_speed": 2.7345039187119244, "streak": 1}, {"run_id": 1590402537000, "name": "run from gpx", "distance": 2903.6013076971317, "moving_time": "0:17:54", "type": "Run", "start_date": "2020-05-25 10:28:57", "start_date_local": "2020-05-25 18:28:57", "location_country": "\u6d77\u6ca7\u533a, \u53a6\u95e8\u5e02, \u5d69\u5c7f\u8857\u9053, \u53a6\u95e8\u5e02, \u798f\u5efa\u7701, 361026, \u4e2d\u56fd", "summary_polyline": "k_htCankoUiA^_ArA`@oAkNj@qQfE}MtBi@u@GoDqAl@?gEkAeRJeBzPkCnP{GfPmJ^DR`H", "average_heartrate": 169.0, "average_speed": 2.7035393926416496, "streak": 1}, {"run_id": 1596108182000, "name": "run from gpx", "distance": 1918.7074868594527, "moving_time": "0:11:46", "type": "Run", "start_date": "2020-07-30 11:23:02", "start_date_local": "2020-07-30 19:23:02", "location_country": "\u89d2\u84bf\u8def, \u6d77\u6ca7\u533a, \u53a6\u95e8\u5e02, \u6d77\u6ca7\u533a, \u53a6\u95e8\u5e02, \u798f\u5efa\u7701, 361026, \u4e2d\u56fd", "summary_polyline": "yxitC}pkoU_@iBh@yDqAm@Ky@i@RIU|@m@_@mATuAnFElHqA~AeA`LgDfT{M`@NG`A|A|Eu@dDhAlDd@V", "average_heartrate": 185.0, "average_speed": 2.717715987053049, "streak": 1}, {"run_id": 1605738708000, "name": "run from gpx", "distance": 3289.6108028924655, "moving_time": "0:19:15", "type": "Run", "start_date": "2020-11-18 22:31:48", "start_date_local": "2020-11-19 06:31:48", "location_country": "\u6d77\u6ca7\u533a, \u53a6\u95e8\u5e02, \u5d69\u5c7f\u8857\u9053, \u53a6\u95e8\u5e02, \u798f\u5efa\u7701, 361026, \u4e2d\u56fd", "summary_polyline": "clgtC{vkoU{@DC`Bm@j@oNpAwA}OD{D\\m@kAyJI_JWc@_BVaM`IgKhFmItB{KxADzAdLoAxGuB~IwDhQuK", "average_heartrate": 159.0, "average_speed": 2.848147881292178, "streak": 1}, {"run_id": 1605825554000, "name": "run from gpx", "distance": 3105.1551102128374, "moving_time": "0:18:53", "type": "Run", "start_date": "2020-11-19 22:39:14", "start_date_local": "2020-11-20 06:39:14", "location_country": "\u6d77\u6ca7\u533a, \u53a6\u95e8\u5e02, \u5d69\u5c7f\u8857\u9053, \u53a6\u95e8\u5e02, \u798f\u5efa\u7701, 361026, \u4e2d\u56fd", "summary_polyline": "slgtCqvkoUc@BP|@_BvAiLr@w@Wo@sIq@_Db@aGc@_Ck@oQ]g@sGjBy@tAeErCmGjDcHfCB~@j@RjHkCtU}Mb@B~@vShG[", "average_heartrate": 164.0, "average_speed": 2.7406488174870587, "streak": 2}, {"run_id": 1606001306000, "name": "run from gpx", "distance": 2990.0080972046976, "moving_time": "0:23:49", "type": "Run", "start_date": "2020-11-21 23:28:26", "start_date_local": "2020-11-22 07:28:26", "location_country": "\u6d77\u6ca7\u533a, \u53a6\u95e8\u5e02, \u5d69\u5c7f\u8857\u9053, \u53a6\u95e8\u5e02, \u798f\u5efa\u7701, 361026, \u4e2d\u56fd", "summary_polyline": "{ngtCyskoUMnB}He@}DRG_FmAkHG}Cb@uA{BuWuEtBgTxMmE~AHbAb@PzEcBdYuO^fAz@dQrBR", "average_heartrate": 137.0, "average_speed": 2.0923779546568912, "streak": 1}, {"run_id": 1606083313000, "name": "run from gpx", "distance": 3867.821345813424, "moving_time": "0:23:58", "type": "Run", "start_date": "2020-11-22 22:15:13", "start_date_local": "2020-11-23 06:15:13", "location_country": "\u6d77\u6ca7\u533a, \u53a6\u95e8\u5e02, \u5d69\u5c7f\u8857\u9053, \u53a6\u95e8\u5e02, \u798f\u5efa\u7701, 361026, \u4e2d\u56fd", "summary_polyline": "qlgtCwvkoUc@FcAhCaNfA}A_O\\sFaAqFI{Nk@iAqGtCsSnMgI|BwKdBFtA`LyArH{BjImDhQkK^?LpAl@fQh@VnHm@Th@", "average_heartrate": 164.0, "average_speed": 2.6897227717756773, "streak": 2}, {"run_id": 1606170432000, "name": "run from gpx", "distance": 3177.184499183878, "moving_time": "0:19:50", "type": "Run", "start_date": "2020-11-23 22:27:12", "start_date_local": "2020-11-24 06:27:12", "location_country": "\u6d77\u6ca7\u533a, \u53a6\u95e8\u5e02, \u5d69\u5c7f\u8857\u9053, \u53a6\u95e8\u5e02, \u798f\u5efa\u7701, 361026, \u4e2d\u56fd", "summary_polyline": "olgtCovkoUYHHp@mAjAcMpAc@@U_@wAyOf@_Eu@eFOiOk@iAuFzBqB|BgHhEaMrFJhAdLuEdOyIvCaAlAzSnIg@", "average_heartrate": 155.0, "average_speed": 2.669902940490654, "streak": 3}, {"run_id": 1606344716000, "name": "run from gpx", "distance": 3781.346789431011, "moving_time": "0:23:05", "type": "Run", "start_date": "2020-11-25 22:51:56", "start_date_local": "2020-11-26 06:51:56", "location_country": "\u6d77\u6ca7\u533a, \u53a6\u95e8\u5e02, \u5d69\u5c7f\u8857\u9053, \u53a6\u95e8\u5e02, \u798f\u5efa\u7701, 361026, \u4e2d\u56fd", "summary_polyline": "kmgtCewkoU[CSxAw@dAoKpAiAU]aH}AuG~@gEsA{NAsEc@o@_UpMoM~EiNlBFbAvIk@`NyDxXwOf@hB`AvO|I^", "average_heartrate": 156.0, "average_speed": 2.7302142883978417, "streak": 1}, {"run_id": 1606516998000, "name": "run from gpx", "distance": 3805.1722029205616, "moving_time": "0:23:27", "type": "Run", "start_date": "2020-11-27 22:43:18", "start_date_local": "2020-11-28 06:43:18", "location_country": "\u6d77\u6ca7\u533a, \u53a6\u95e8\u5e02, \u5d69\u5c7f\u8857\u9053, \u53a6\u95e8\u5e02, \u798f\u5efa\u7701, 361026, \u4e2d\u56fd", "summary_polyline": "wlgtCavkoUu@Ra@~B{Mr@_@WYcHcAoDKgDd@uFiAqJDsEg@{@}EhAeTbNeLbD{IhANbAvIm@tKwCrZuPd@FHj@j@xLp@bE`Iy@", "average_heartrate": 153.0, "average_speed": 2.7044578556649337, "streak": 1}, {"run_id": 1606688399000, "name": "run from gpx", "distance": 3127.3778064033877, "moving_time": "0:19:12", "type": "Run", "start_date": "2020-11-29 22:19:59", "start_date_local": "2020-11-30 06:19:59", "location_country": "\u6d77\u6ca7\u533a, \u53a6\u95e8\u5e02, \u5d69\u5c7f\u8857\u9053, \u53a6\u95e8\u5e02, \u798f\u5efa\u7701, 361026, \u4e2d\u56fd", "summary_polyline": "gmgtCawkoUk@jBg@\\eGx@cE?o@_@FqEiAqDNsIk@aEIsFBqCXi@s@mC}G`BySdNcEvADf@x@RhDmAxYuOzA`Gb@nK`@VvDk@dBF", "average_heartrate": 155.0, "average_speed": 2.714737679169607, "streak": 1}, {"run_id": 1606861254000, "name": "run from gpx", "distance": 3777.0142163511423, "moving_time": "0:24:11", "type": "Run", "start_date": "2020-12-01 22:20:54", "start_date_local": "2020-12-02 06:20:54", "location_country": "\u6d77\u6ca7\u533a, \u53a6\u95e8\u5e02, \u5d69\u5c7f\u8857\u9053, \u53a6\u95e8\u5e02, \u798f\u5efa\u7701, 361026, \u4e2d\u56fd", "summary_polyline": "ingtCqvkoUcAfCsLnAg@YuBwP}@{AfAyBLoAS{Ng@{CmZnPaIxBaNtBMjALTxImAxKwCf[iP\\lA\\zHrAbH|Gy@", "average_heartrate": 158.0, "average_speed": 2.603042189077286, "streak": 1}, {"run_id": 1606948621000, "name": "run from gpx", "distance": 3136.4197905057986, "moving_time": "0:19:34", "type": "Run", "start_date": "2020-12-02 22:37:01", "start_date_local": "2020-12-03 06:37:01", "location_country": "\u6d77\u6ca7\u533a, \u53a6\u95e8\u5e02, \u5d69\u5c7f\u8857\u9053, \u53a6\u95e8\u5e02, \u798f\u5efa\u7701, 361026, \u4e2d\u56fd", "summary_polyline": "qlgtCoukoUi@HiAhC}Dg@aHr@UiEaA_F?aF`@oBwAeOJmEa@_AkW~N_IxCMz@p@V`GwBbVcNz@MdBhThHm@", "average_heartrate": 156.0, "average_speed": 2.6715671128669496, "streak": 2}, {"run_id": 1607034270000, "name": "run from gpx", "distance": 3073.2188975078066, "moving_time": "0:18:34", "type": "Run", "start_date": "2020-12-03 22:24:30", "start_date_local": "2020-12-04 06:24:30", "location_country": "\u6d77\u6ca7\u533a, \u53a6\u95e8\u5e02, \u5d69\u5c7f\u8857\u9053, \u53a6\u95e8\u5e02, \u798f\u5efa\u7701, 361026, \u4e2d\u56fd", "summary_polyline": "sngtCevkoUe@bCaLlA{@WaBwTNuD_BaSiEn@yCnC{KrG}IlDP|@rKkD~SiMd@nA?~G|@bIbHq@", "average_heartrate": 161.0, "average_speed": 2.7587243245132913, "streak": 3}, {"run_id": 1607294704000, "name": "run from gpx", "distance": 3135.419907980164, "moving_time": "0:19:19", "type": "Run", "start_date": "2020-12-06 22:45:04", "start_date_local": "2020-12-07 06:45:04", "location_country": "\u6d77\u6ca7\u533a, \u53a6\u95e8\u5e02, \u5d69\u5c7f\u8857\u9053, \u53a6\u95e8\u5e02, \u798f\u5efa\u7701, 361026, \u4e2d\u56fd", "summary_polyline": "ungtC{xkoUw@|D{CrA{GJc@]@}EyA_Eh@iIyAuOJqEWc@cF`AmUzNyDlAB`@j@l@pHcC~UiN\\PVlBXnJj@lDlHO", "average_heartrate": 146.0, "average_speed": 2.70528033475424, "streak": 1}, {"run_id": 1628508632000, "name": "run from gpx", "distance": 2540.0897610845323, "moving_time": "0:26:11", "type": "Run", "start_date": "2021-08-09 11:30:32", "start_date_local": "2021-08-09 19:30:32", "location_country": "X435, \u6d77\u6ca7\u533a, \u53a6\u95e8\u5e02, \u6d77\u6ca7\u533a, \u53a6\u95e8\u5e02, \u798f\u5efa\u7701, 361026, \u4e2d\u56fd", "summary_polyline": "m}gtCyokoUgAcCuByNb@i@NcHs@eP_Db@uOrJcMrF`IuA~PwJlFWh@hPjAG", "average_heartrate": null, "average_speed": 1.6168617193408863, "streak": 1}, {"run_id": 1628595769000, "name": "run from gpx", "distance": 3018.3992296176884, "moving_time": "0:20:14", "type": "Run", "start_date": "2021-08-10 11:42:49", "start_date_local": "2021-08-10 19:42:49", "location_country": "\u6d77\u6ca7\u533a, \u53a6\u95e8\u5e02, \u5d69\u5c7f\u8857\u9053, \u53a6\u95e8\u5e02, \u798f\u5efa\u7701, 361026, \u4e2d\u56fd", "summary_polyline": "{ogtCovkoUFvAW^}FjAoENqBsQb@iH{@wPq@wAuYlPmH|BnMgFvR}KzAfBp@~QbCR", "average_heartrate": null, "average_speed": 2.4863255598168768, "streak": 2}, {"run_id": 1628770274000, "name": "run from gpx", "distance": 3285.6131797137386, "moving_time": "0:23:10", "type": "Run", "start_date": "2021-08-12 12:11:14", "start_date_local": "2021-08-12 20:11:14", "location_country": "\u6d77\u6ca7\u533a, \u53a6\u95e8\u5e02, \u5d69\u5c7f\u8857\u9053, \u53a6\u95e8\u5e02, \u798f\u5efa\u7701, 361026, \u4e2d\u56fd", "summary_polyline": "wkgtCyvkoU}@LQdAq@j@cNnA{@kHsAoc@g@q@w@DcX~OoL`DdQiGhJ}F|AqB`EkAfBjCP|Jn@dEp@XzDE", "average_heartrate": null, "average_speed": 2.3637504890026895, "streak": 1}, {"run_id": 1628855166000, "name": "run from gpx", "distance": 3320.6974144901674, "moving_time": "0:21:53", "type": "Run", "start_date": "2021-08-13 11:46:06", "start_date_local": "2021-08-13 19:46:06", "location_country": "\u6d77\u6ca7\u533a, \u53a6\u95e8\u5e02, \u5d69\u5c7f\u8857\u9053, \u53a6\u95e8\u5e02, \u798f\u5efa\u7701, 361026, \u4e2d\u56fd", "summary_polyline": "slgtCwukoUCi@y@PE`B}@n@qLjA_@YqAeOLqF_AeUe@m@}A^cTjMmOzEtOqFxT_M|BhANzMz@nCtFT", "average_heartrate": null, "average_speed": 2.529091709436533, "streak": 2}, {"run_id": 1628934861000, "name": "run from gpx", "distance": 3215.9522580072, "moving_time": "0:20:38", "type": "Run", "start_date": "2021-08-14 09:54:21", "start_date_local": "2021-08-14 17:54:21", "location_country": "X435, \u6d77\u6ca7\u533a, \u53a6\u95e8\u5e02, \u6d77\u6ca7\u533a, \u53a6\u95e8\u5e02, \u798f\u5efa\u7701, 361026, \u4e2d\u56fd", "summary_polyline": "yqgtCgrkoUIVg@OgIdA_@UkAmEq@cHCuCd@eB}@sTg@aAkALaUdNiNnEYOjOyEpLeH~BcCfCq@rAxAtAjRlAh@vGc@", "average_heartrate": null, "average_speed": 2.5976997237537964, "streak": 3}, {"run_id": 1629027679000, "name": "run from gpx", "distance": 3235.989422115505, "moving_time": "0:21:08", "type": "Run", "start_date": "2021-08-15 11:41:19", "start_date_local": "2021-08-15 19:41:19", "location_country": "\u6d77\u6ca7\u533a, \u53a6\u95e8\u5e02, \u5d69\u5c7f\u8857\u9053, \u53a6\u95e8\u5e02, \u798f\u5efa\u7701, 361026, \u4e2d\u56fd", "summary_polyline": "sogtCoskoUcCdA_Ir@c@QyBcNN_Ma@_NO{@o@e@eC|@aTlMiJrCsBRfNcEvKmG|DsDpCo@tBjCZpPjAf@fGK", "average_heartrate": null, "average_speed": 2.5520421310059187, "streak": 4}, {"run_id": 1629115319000, "name": "run from gpx", "distance": 3327.192955943744, "moving_time": "0:21:08", "type": "Run", "start_date": "2021-08-16 12:01:59", "start_date_local": "2021-08-16 20:01:59", "location_country": "\u6d77\u6ca7\u533a, \u53a6\u95e8\u5e02, \u5d69\u5c7f\u8857\u9053, \u53a6\u95e8\u5e02, \u798f\u5efa\u7701, 361026, \u4e2d\u56fd", "summary_polyline": "wlgtCmvkoUOWi@PSfBq@^cLlAc@QiAuI@yKy@eQSiCk@a@gAPsTxMgOjE|JqClFeCfIcF|AqBfDeA~BdBXjO\\rAn@d@jGW", "average_heartrate": null, "average_speed": 2.623969208157527, "streak": 5}, {"run_id": 1629201296000, "name": "run from gpx", "distance": 2989.420410167149, "moving_time": "0:18:43", "type": "Run", "start_date": "2021-08-17 11:54:56", "start_date_local": "2021-08-17 19:54:56", "location_country": "X435, \u6d77\u6ca7\u533a, \u53a6\u95e8\u5e02, \u6d77\u6ca7\u533a, \u53a6\u95e8\u5e02, \u798f\u5efa\u7701, 361026, \u4e2d\u56fd", "summary_polyline": "u|gtC_pkoU{AYgAeOHcFg@qAYaQ{@mBgTpMkF|BgJ`ChMwDxHcExFkFzDuAjC|BEzC~@nLjEIbBb@", "average_heartrate": null, "average_speed": 2.66199502241064, "streak": 6}]